[
  {
    "ูุงู": "ูููฺฉุณุ ID.4 Crozz",
    "ุณุงู ุณุงุฎุช": "2024",
    "ูุฏู": "PURE",
    "ุชุงู": "ูุญุธุงุช ูพุด",
    "ููุช": 3780000000.0,
    "ุขุฏุฑุณ": "ุงุตููุงู / ุจุฒุฑฺฏุฑุงู ุฎูุฌ ูุงุฑุณ ( ูุฑู)",
    "ุชูุถุญุงุช": " ุชูุถุญุงุช ุงูุงุฏู ุชุญูู ุจุง ูพูุงฺฉ ู ูุฏุงุฑฺฉ ฺฉุงูู ุชุญูู ุฏุฑ ููุงูุฏฺฏ",
    "ฺฉุงุฑฺฉุฑุฏ": "ุตูุฑ ฺฉูููุชุฑ",
    "ููุน ุณูุฎุช": "ุจุฑู",
    "ฺฏุฑุจฺฉุณ": "ุงุชููุงุชฺฉ",
    "ูุถุนุช ุจุฏูู": "ุจุฏูู ุฑูฺฏ",
    "ุฑูฺฏ ุจุฏูู": "ุณูุฏ",
    "ุฑูฺฏ ุฏุงุฎู": "ุฏุงุฎู ูุดฺฉ",
    "ูพุดุฑุงูู": "1 ููุชูุฑ ุงูฺฉุชุฑฺฉ",
    "ุดุชุงุจ": "9 ุซุงูู"
  },
  {
    "ูุงู": "ฺฉ ุงู ุณุ T9",
    "ุณุงู ุณุงุฎุช": "1404",
    "ูุฏู": "2 ูุชุฑ ุชูุฑุจู",
    "ุชุงู": "ูุญุธุงุช ูพุด",
    "ููุช": 2750000000.0,
    "ุขุฏุฑุณ": "ุชูุฑุงู / 17 ุดูุฑูุฑ",
    "ุชูุถุญุงุช": " ุชูุถุญุงุช ๐ููุงูุฏฺฏ ฺฉุฑูุงู ููุชูุฑ๐\nโชโชโชโชโชโชโชโชโชโชโชโชโชโชโชโชโชโชโชโชโชโชโชโชRafiee Motorโชโชโชโชโชโชโชโชโชโชโชโชโชโชโชโชโชโชโชโชโชโชโชโช\nโุซุจุช ุชูุงู ุงุณูุงุฏ ุจู ูุงู ูุชูุงุถ \nโุชุญูู ฒฐ ุฑูุฒ ฺฉุงุฑ ุงุฒ ููุงูุฏฺฏ ุฑุณู \nโุฏุงุฑุง ฺฏุงุฑุงูุช ุดุฑฺฉุช \nโูุฑุตุช ููุงุณุจ ุจุฑุง ุณุฑูุงู ฺฏุฐุงุฑ ุจุง ุชุนุฏุงุฏ ูุญุฏูุฏ \nโุนูุฏ ูุฑุงุฑุฏุงุฏ ุฏุฑ ููุงูุฏฺฏ ุฑุณู\nโพโปโพโปโพโปโพโปโพโปโพโปโพโปโพโปโพโปโพโปโพโปโพโปโพโปโพโปโพโปโพโปโพโปโพ\nโุฌูุช ุงุทูุงุนุงุช ุจุดุชุฑ ุจุง ูุง ุชูุงุณ ุจฺฏุฑุฏ.",
    "ฺฉุงุฑฺฉุฑุฏ": "ุตูุฑ ฺฉูููุชุฑ",
    "ููุน ุณูุฎุช": "ุจูุฒู",
    "ฺฏุฑุจฺฉุณ": "ุงุชููุงุชฺฉ",
    "ูุถุนุช ุจุฏูู": "ุจุฏูู ุฑูฺฏ",
    "ุฑูฺฏ ุจุฏูู": "ูุดฺฉ",
    "ุฑูฺฏ ุฏุงุฎู": "ุฏุงุฎู ูุดฺฉ",
    "ุญุฌู ููุชูุฑ": "2.0 ูุชุฑ",
    "ูพุดุฑุงูู": "4 ุณููุฏุฑ ุชูุฑุจูุดุงุฑฺ (HFC4DB2)"
  },
  {
    "ูุงู": "ุจ ุง ุณุ X3 PRO",
    "ุณุงู ุณุงุฎุช": "1404",
    "ูุฏู": "1.5 ูุชุฑ",
    "ุชุงู": "ูุญุธุงุช ูพุด",
    "ููุช": "ุชูุงูู",
    "ุขุฏุฑุณ": "ุชูุฑุงู / ูพููฺฉ",
    "ุชูุถุญุงุช": " ุชูุถุญุงุช โช๏ธโพ๏ธโผ๏ธโผ๏ธ ููุงูุฏฺฏ ูุฌุงุฒ ฺฉุฑูุงู ููุชูุฑ ฺฉุฏ 314ุฑูุน โผ๏ธโผ๏ธโพ๏ธโช๏ธ\nโ-ุงูฺฉุงู ุจุงุฒุฏุฏ ูุจู ุงุฒ ุฎุฑุฏ\n____________________________________\nุฌูุช ฺฉุณุจ ุงุทูุงุนุงุช ุจุดุชุฑ ุจุง ููฺฉุงุฑุงู ูุง ุฏุฑ ุชูุงุณ ุจุงุดุฏ.",
    "ฺฉุงุฑฺฉุฑุฏ": "ุตูุฑ ฺฉูููุชุฑ",
    "ููุน ุณูุฎุช": "ุจูุฒู",
    "ฺฏุฑุจฺฉุณ": "ุงุชููุงุชฺฉ",
    "ูุถุนุช ุจุฏูู": "ุจุฏูู ุฑูฺฏ",
    "ุฑูฺฏ ุจุฏูู": "ูุดฺฉ",
    "ุฑูฺฏ ุฏุงุฎู": "ุฏุงุฎู ูุดฺฉ",
    "ุญุฌู ููุชูุฑ": "1.5 ูุชุฑ",
    "ูพุดุฑุงูู": "4 ุณููุฏุฑ (4G15)",
    "ุดุชุงุจ": "12.6 ุซุงูู",
    "ูุตุฑู ุชุฑฺฉุจ": "6.1 ูุชุฑ ุฏุฑ ุตุฏ ฺฉูููุชุฑ"
  },
  {
    "ูุงู": "ูุงูุงุฑุ ุงูุง",
    "ุณุงู ุณุงุฎุช": "1404",
    "ูุฏู": "ุงุชููุงุชฺฉ",
    "ุชุงู": "ูุญุธุงุช ูพุด",
    "ููุช": "ุชูุงูู",
    "ุขุฏุฑุณ": "ุชูุฑุงู / ุงูุฏุฑุฒฺฏู",
    "ุชูุถุญุงุช": " ุชูุถุญุงุช โุงูุฏ ฺฏุงูุฑ\nุจุด ุงุฒ ฑต ุณุงู ุณุงุจูู ุฏุฑ ุฎุฑุฏ ู ูุฑูุด ูุงุดู\nุนุถู ุฑุณู ุงุชุญุงุฏู\nุชุญูู ููุฑ ุจุง ุงูฺฉุงู ฺฉุงุฑุดูุงุณ\nโููุช ุขุฎุฑ ุฑุง ุงุฒ ูุง ุจุฎูุงูุฏ",
    "ฺฉุงุฑฺฉุฑุฏ": "ุตูุฑ ฺฉูููุชุฑ",
    "ููุน ุณูุฎุช": "ุจูุฒู",
    "ฺฏุฑุจฺฉุณ": "ุงุชููุงุชฺฉ",
    "ูุถุนุช ุจุฏูู": "ุจุฏูู ุฑูฺฏ",
    "ุฑูฺฏ ุจุฏูู": "ูุดฺฉ",
    "ุฑูฺฏ ุฏุงุฎู": "ุฏุงุฎู ูุดฺฉ",
    "ุญุฌู ููุชูุฑ": "1.5 ูุชุฑ",
    "ูพุดุฑุงูู": "4 ุณููุฏุฑ ุชูุฑุจูุดุงุฑฺ (4A95TD)",
    "ุดุชุงุจ": "9.5 ุซุงูู"
  },
  {
    "ูุงู": "ููฺฉุงููุ L7",
    "ุณุงู ุณุงุฎุช": "1404",
    "ูุฏู": "1.6 ูุชุฑ ุชูุฑุจู",
    "ุชุงู": "ูุญุธุงุช ูพุด",
    "ููุช": 1800000000.0,
    "ุขุฏุฑุณ": "ุงุตููุงู / ุจุฒุฑฺฏุฑุงู ุฎูุฌ ูุงุฑุณ ( ูุฑู)",
    "ุชูุถุญุงุช": " ุชูุถุญุงุช โ ุซุจุช ูุงู ุฎูุฏุฑู ููฺฉุงูู ุจุงุฒ ุดุฏโ\n๐ ูุฑูุด ูุทุน ู ุจุฏูู ูุฑุนู ฺฉุด ููฺฉุงูู L7 ุจู ุตูุฑุช ุงูุณุงุท ุฏุฑ ููุงูุฏฺฏ ทฒด ุงููุงุณ ูพุงุฑุณ๐\n๐ทุงูุณุงุท ณถ ูุงูู\n๐ทุจุฏูู ูุญุฏูุฏุช ุซุจุช ูุงู\n๐ทุฎุงุฑุฌ ุงุฒ ุณุงูุงูู ู ุจุฏูู ูุฑุนู ฺฉุด\n๐ทุฑูฺฏ ุจู ุงูุชุฎุงุจ ูุดุชุฑ\n๐ทุชุญูู ฑฐ ุฑูุฒู\n*ุซุจุช ุงุทูุงุนุงุช ุฌูุช ูพุด ุซุจุช ูุงู ููุท ุจุง ุงุฑุณุงู ฺฉโ ูุฏุฑฺฉ ุดูุงุณุง ุงูฺฉุงู ูพุฐุฑ ุงุณุช*\nุฌูุช ฺฉุณุจ ุงุทูุงุนุงุช ุจุดุชุฑ ุจุง ฺฉุงุฑุดูุงุณุงู ูุง ุฏุฑ ุงุฑุชุจุงุท ุจุงุดุฏ",
    "ฺฉุงุฑฺฉุฑุฏ": "ุตูุฑ ฺฉูููุชุฑ",
    "ููุน ุณูุฎุช": "ุจูุฒู",
    "ฺฏุฑุจฺฉุณ": "ุงุชููุงุชฺฉ",
    "ูุถุนุช ุจุฏูู": "ุจุฏูู ุฑูฺฏ",
    "ุฑูฺฏ ุจุฏูู": "ูุดฺฉ",
    "ุฑูฺฏ ุฏุงุฎู": "ุฏุงุฎู ูุดฺฉ",
    "ุญุฌู ููุชูุฑ": "1.6 ูุชุฑ",
    "ูพุดุฑุงูู": "4 ุณููุฏุฑ ุชูุฑุจูุดุงุฑฺ (4J16)",
    "ุดุชุงุจ": "8 ุซุงูู",
    "ูุตุฑู ุชุฑฺฉุจ": "7.4 ูุชุฑ ุฏุฑ ุตุฏ ฺฉูููุชุฑ"
  },
  {
    "ูุงู": "ุณููุฏุ ุณูุฑู",
    "ุณุงู ุณุงุฎุช": "1404",
    "ูุฏู": "ูพูุงุณ EF7 ุฏูฺฏุงูู ุณูุฒ",
    "ุชุงู": "ูุญุธุงุช ูพุด",
    "ููุช": 898000000.0,
    "ุขุฏุฑุณ": "ุชูุฑุงู / ุดูุฑฺฉ ุฑุงูโุขูู",
    "ุชูุถุญุงุช": " ุชูุถุญุงุช ููุฏ ู ุงูุณุงุท ุุจู ุดุฑุท ฺฉุงุฑุดูุงุณ ุุจู ุดุฑุท ุฑูุชุุณูุฏ ุงุฒุงุฏุูุนุงูุถู ุจุง ุฎูุฏุฑู ุดูุง\nุดุฌุฑ",
    "ฺฉุงุฑฺฉุฑุฏ": "ุตูุฑ ฺฉูููุชุฑ",
    "ููุน ุณูุฎุช": "ุฏูฺฏุงูู ุณูุฒ",
    "ฺฏุฑุจฺฉุณ": "ุฏูุฏู ุง",
    "ูุถุนุช ุจุฏูู": "ุจุฏูู ุฑูฺฏ",
    "ุฑูฺฏ ุจุฏูู": "ุณูุฏ",
    "ุฑูฺฏ ุฏุงุฎู": "ุฏุงุฎู ูุดฺฉ",
    "ุญุฌู ููุชูุฑ": "1.7 ูุชุฑ",
    "ูพุดุฑุงูู": "4 ุณููุฏุฑ EF7 ุฏูฺฏุงูู ุณูุฒ",
    "ุดุชุงุจ": "12.8 ุซุงูู",
    "ูุตุฑู ุชุฑฺฉุจ": "7.5 ูุชุฑ ุฏุฑ ุตุฏ ฺฉูููุชุฑ"
  },
  {
    "ูุงู": "ููฺฉุงููุ L7",
    "ุณุงู ุณุงุฎุช": "1404",
    "ูุฏู": "1.6 ูุชุฑ ุชูุฑุจู",
    "ุชุงู": "ูุญุธุงุช ูพุด",
    "ููุช": 1800000000.0,
    "ุขุฏุฑุณ": "ุงุตููุงู / ุจุฒุฑฺฏุฑุงู ุฎูุฌ ูุงุฑุณ ( ูุฑู)",
    "ุชูุถุญุงุช": " ุชูุถุญุงุช โ ุซุจุช ูุงู ุฎูุฏุฑู ููฺฉุงูู ุจุงุฒ ุดุฏโ\n๐ ูุฑูุด ูุทุน ู ุจุฏูู ูุฑุนู ฺฉุด ููฺฉุงูู L7 ุจู ุตูุฑุช ุงูุณุงุท ุฏุฑ ููุงูุฏฺฏ ทฒด ุงููุงุณ ูพุงุฑุณ๐\n๐ทุงูุณุงุท ณถ ูุงูู\n๐ทุจุฏูู ูุญุฏูุฏุช ุซุจุช ูุงู\n๐ทุฎุงุฑุฌ ุงุฒ ุณุงูุงูู ู ุจุฏูู ูุฑุนู ฺฉุด\n๐ทุฑูฺฏ ุจู ุงูุชุฎุงุจ ูุดุชุฑ\n๐ทุชุญูู ฑฐ ุฑูุฒู\n*ุซุจุช ุงุทูุงุนุงุช ุฌูุช ูพุด ุซุจุช ูุงู ููุท ุจุง ุงุฑุณุงู ฺฉโ ูุฏุฑฺฉ ุดูุงุณุง ุงูฺฉุงู ูพุฐุฑ ุงุณุช*\nุฌูุช ฺฉุณุจ ุงุทูุงุนุงุช ุจุดุชุฑ ุจุง ฺฉุงุฑุดูุงุณุงู ูุง ุฏุฑ ุงุฑุชุจุงุท ุจุงุดุฏ",
    "ฺฉุงุฑฺฉุฑุฏ": "ุตูุฑ ฺฉูููุชุฑ",
    "ููุน ุณูุฎุช": "ุจูุฒู",
    "ฺฏุฑุจฺฉุณ": "ุงุชููุงุชฺฉ",
    "ูุถุนุช ุจุฏูู": "ุจุฏูู ุฑูฺฏ",
    "ุฑูฺฏ ุจุฏูู": "ุณูุฏ",
    "ุฑูฺฏ ุฏุงุฎู": "ุฏุงุฎู ูุดฺฉ",
    "ุญุฌู ููุชูุฑ": "1.6 ูุชุฑ",
    "ูพุดุฑุงูู": "4 ุณููุฏุฑ ุชูุฑุจูุดุงุฑฺ (4J16)",
    "ุดุชุงุจ": "8 ุซุงูู",
    "ูุตุฑู ุชุฑฺฉุจ": "7.4 ูุชุฑ ุฏุฑ ุตุฏ ฺฉูููุชุฑ"
  },
  {
    "ูุงู": "ฺฉ ุงู ุณุ ุงฺฏู",
    "ุณุงู ุณุงุฎุช": "1404",
    "ูุฏู": "1.5 ูุชุฑ",
    "ุชุงู": "ูุญุธุงุช ูพุด",
    "ููุช": 1050000000.0,
    "ุขุฏุฑุณ": "ุชูุฑุงู / ูพููฺฉ",
    "ุชูุถุญุงุช": " ุชูุถุญุงุช โช๏ธโพ๏ธโผ๏ธโผ๏ธ ููุงูุฏฺฏ ูุฌุงุฒ ฺฉุฑูุงู ููุชูุฑ ฺฉุฏ 1752ุฑูุน โผ๏ธโผ๏ธโพ๏ธโช๏ธ\nโ-ูุฑูุด ููุฏ * ุชุญูู 20 ุฑูุฒู ฺฉุงุฑ\nโ-ุงูุชุฎุงุจ ุฑูฺฏ ุจุฏูู ุงุฎุชูุงู ููุช * \nโ-ุณูุฏ ุขุฒุงุฏ ู ุจู ูุงู ุฎุฑุฏุงุฑ",
    "ฺฉุงุฑฺฉุฑุฏ": "ุตูุฑ ฺฉูููุชุฑ",
    "ููุน ุณูุฎุช": "ุจูุฒู",
    "ฺฏุฑุจฺฉุณ": "ุงุชููุงุชฺฉ",
    "ูุถุนุช ุจุฏูู": "ุจุฏูู ุฑูฺฏ",
    "ุฑูฺฏ ุจุฏูู": "ุณูุฏ",
    "ุฑูฺฏ ุฏุงุฎู": "ุฏุงุฎู ูุดฺฉ",
    "ุญุฌู ููุชูุฑ": "1.5 ูุชุฑ",
    "ูพุดุฑุงูู": "4 ุณููุฏุฑ",
    "ุดุชุงุจ": "12.5 ุซุงูู",
    "ูุตุฑู ุชุฑฺฉุจ": "6.8 ูุชุฑ ุฏุฑ ุตุฏ ฺฉูููุชุฑ"
  },
  {
    "ูุงู": "ูพูุฑุดูุ ุจุงฺฉุณุชุฑ",
    "ุณุงู ุณุงุฎุช": "2017",
    "ูุฏู": "718S",
    "ุชุงู": "ูุญุธุงุช ูพุด",
    "ููุช": 20000000000.0,
    "ุขุฏุฑุณ": "ุชูุฑุงู / ุฒุนูุฑุงูู",
    "ุชูุถุญุงุช": " ุชูุถุญุงุช ุจุฏูู ู ูู ุจ ููุต ุจู ุดุฑุท\nุงุณูพุฑุช ู ุงุณูพุฑุช ูพูุงุณ ู ูพุงูุฑ ุจูุณุช ุฑู ูุฑูููุ ฺุฑุงุบpdls plus  ุฑูฺฏ ุณูุงุฑุด \nูุฑฺฏูููโ ูุฒุงุญูุช ูพฺฏุฑุฏ ูุงููู ุฎูุงูุฏ ุฏุงุดุช",
    "ฺฉุงุฑฺฉุฑุฏ": "39,000 km",
    "ููุน ุณูุฎุช": "ุจูุฒู",
    "ฺฏุฑุจฺฉุณ": "ุงุชููุงุชฺฉ",
    "ูุถุนุช ุจุฏูู": "ุจุฏูู ุฑูฺฏ",
    "ุฑูฺฏ ุจุฏูู": "ููุฑุขุจ",
    "ุฑูฺฏ ุฏุงุฎู": "ุฏุงุฎู ูุฑูุฒ",
    "ุญุฌู ููุชูุฑ": "2.5 ูุชุฑ",
    "ูพุดุฑุงูู": "4 ุณููุฏุฑ ุชุฎุช ุชูุฑุจูุดุงุฑฺ",
    "ุดุชุงุจ": "4.4 ุซุงูู",
    "ูุตุฑู ุชุฑฺฉุจ": "7.3 ูุชุฑ ุฏุฑ ุตุฏ ฺฉูููุชุฑ"
  },
  {
    "ูุงู": "ฺุฑุ ุขุฑุฒู 5T ุงุณูพุฑุช FL",
    "ุณุงู ุณุงุฎุช": "1404",
    "ูุฏู": "IE",
    "ุชุงู": "ุฏูุงู ูพุด",
    "ููุช": 1640000000.0,
    "ุขุฏุฑุณ": "ุชูุฑุงู / ุดูุฑฺฉ ุฑุงูโุขูู",
    "ุชูุถุญุงุช": " ุชูุถุญุงุช ููุฏ ู ุงูุณุงุท ุุจู ุดุฑุท ฺฉุงุฑุดูุงุณ ุุจู ุดุฑุท ุฑูุชุุณูุฏ ุงุฒุงุฏุูุนุงูุถู ุจุง ุฎูุฏุฑู ุดูุง\nุดุฌุฑ",
    "ฺฉุงุฑฺฉุฑุฏ": "ุตูุฑ ฺฉูููุชุฑ",
    "ููุน ุณูุฎุช": "ุจูุฒู",
    "ฺฏุฑุจฺฉุณ": "ุงุชููุงุชฺฉ",
    "ูุถุนุช ุจุฏูู": "ุจุฏูู ุฑูฺฏ",
    "ุฑูฺฏ ุจุฏูู": "ุณูุฏ",
    "ุฑูฺฏ ุฏุงุฎู": "ุฏุงุฎู ูุดฺฉ",
    "ุญุฌู ููุชูุฑ": "1.5 ูุชุฑ",
    "ูพุดุฑุงูู": "4 ุณููุฏุฑ ุชูุฑุจูุดุงุฑฺ",
    "ุดุชุงุจ": "10.1 ุซุงูู",
    "ูุตุฑู ุชุฑฺฉุจ": "6.9 ูุชุฑ ุฏุฑ ุตุฏ ฺฉูููุชุฑ"
  },
  {
    "ูุงู": "ุฌฺฉุ S5",
    "ุณุงู ุณุงุฎุช": "1403",
    "ูุฏู": "1.5 ูุชุฑ ุงุชููุงุชฺฉ",
    "ุชุงู": "ุฏูุงู ูพุด",
    "ููุช": 1799000000.0,
    "ุขุฏุฑุณ": "ุชูุฑุงู / ุดูุฑฺฉ ุบุฑุจ",
    "ุชูุถุญุงุช": " ุชูุถุญุงุช ููุงูุฏฺฏ ฺฉุฑูุงู ููุชูุฑ ุฎุฏุงูุฏุฏ ฺฉุฏ: ฑทดธ  \nโ๏ธุชุญูู ููุฑ\nโูุฏุงุฑฺฉ ุขูุงุฏู ุงูุชูุงู ",
    "ฺฉุงุฑฺฉุฑุฏ": "ุตูุฑ ฺฉูููุชุฑ",
    "ููุน ุณูุฎุช": "ุจูุฒู",
    "ฺฏุฑุจฺฉุณ": "ุงุชููุงุชฺฉ",
    "ูุถุนุช ุจุฏูู": "ุจุฏูู ุฑูฺฏ",
    "ุฑูฺฏ ุจุฏูู": "ูุดฺฉ",
    "ุฑูฺฏ ุฏุงุฎู": "ุฏุงุฎู ูุดฺฉ",
    "ุญุฌู ููุชูุฑ": "1.5 ูุชุฑ",
    "ูพุดุฑุงูู": "4 ุณููุฏุฑ ุชูุฑุจูุดุงุฑฺ TGDi"
  },
  {
    "ูุงู": "ฺฉ ุงู ุณุ X5",
    "ุณุงู ุณุงุฎุช": "1403",
    "ูุฏู": "1.5 ูุชุฑ ุชูุฑุจู",
    "ุชุงู": "ุฏูุงู ูพุด",
    "ููุช": 1949000000.0,
    "ุขุฏุฑุณ": "ุชูุฑุงู / ุดูุฑฺฉ ุบุฑุจ",
    "ุชูุถุญุงุช": " ุชูุถุญุงุช ููุงูุฏฺฏ ฺฉุฑูุงู ููุชูุฑ ุฎุฏุงูุฏุฏ \nฺฉุฏ :1748\nโ๏ธุชุญูู ููุฑ \nโ๏ธุจุฏูู ูุฒูู ุงุถุงู\nโุชฺฉ ุฑูฺฏุชุฑู ูุญุตูู ฺฉุฑูุงู ููุชูุฑ\nโูุฏุงุฑฺฉ ุขูุงุฏู ุงูุชูุงู ",
    "ฺฉุงุฑฺฉุฑุฏ": "ุตูุฑ ฺฉูููุชุฑ",
    "ููุน ุณูุฎุช": "ุจูุฒู",
    "ฺฏุฑุจฺฉุณ": "ุงุชููุงุชฺฉ",
    "ูุถุนุช ุจุฏูู": "ุจุฏูู ุฑูฺฏ",
    "ุฑูฺฏ ุจุฏูู": "ูููู ุง",
    "ุฑูฺฏ ุฏุงุฎู": "ุฏุงุฎู ูููู ุง",
    "ุญุฌู ููุชูุฑ": "1.5 ูุชุฑ",
    "ูพุดุฑุงูู": "4 ุณููุฏุฑ ุชูุฑุจูุดุงุฑฺ (4GC16D)"
  },
  {
    "ูุงู": "ูพฺูุ 207",
    "ุณุงู ุณุงุฎุช": "1404",
    "ูุฏู": "ูพุงููุฑุงูุง ุฏูุฏู ุง",
    "ุชุงู": "ุฏูุงู ูพุด",
    "ููุช": "ุชูุงูู",
    "ุขุฏุฑุณ": "ุชูุฑุงู / ุชูุญุฏ",
    "ุชูุถุญุงุช": "",
    "ฺฉุงุฑฺฉุฑุฏ": "ุตูุฑ ฺฉูููุชุฑ",
    "ููุน ุณูุฎุช": "ุจูุฒู",
    "ฺฏุฑุจฺฉุณ": "ุฏูุฏู ุง",
    "ูุถุนุช ุจุฏูู": "ุจุฏูู ุฑูฺฏ",
    "ุฑูฺฏ ุจุฏูู": "ุณูุฏ",
    "ุฑูฺฏ ุฏุงุฎู": "ุฏุงุฎู ูุดฺฉ",
    "ุญุฌู ููุชูุฑ": "1.6 ูุชุฑ",
    "ูพุดุฑุงูู": "4 ุณููุฏุฑ TU5",
    "ุดุชุงุจ": "11.6 ุซุงูู",
    "ูุตุฑู ุชุฑฺฉุจ": "6.6 ูุชุฑ ุฏุฑ ุตุฏ ฺฉูููุชุฑ"
  },
  {
    "ูุงู": "ุฌฺฉุ S3",
    "ุณุงู ุณุงุฎุช": "1403",
    "ูุฏู": "ุงุชููุงุชฺฉ",
    "ุชุงู": "ุฏูุงู ูพุด",
    "ููุช": 1399000000.0,
    "ุขุฏุฑุณ": "ุชูุฑุงู / ุดูุฑฺฉ ุบุฑุจ",
    "ุชูุถุญุงุช": " ุชูุถุญุงุช ููุงูุฏฺฏ ุฎุฏุงูุฏุฏ ฺฉุฏ:ฑทดธ\nโุชุญูู ููุฑ ( ูุจู ุงุฒ ุณุงุนุช ฑด ูฺฉุงูุช ูุงูู ุจู ุงุณู ูุดุชุฑ ูุญุชุฑู ููุงู ูุญุธู ุตุงุฏุฑ ูโุดูุฏ)\nุตุฏูุฑ ูพูุงฺฉ ู ุจูู ุชุฑูุงู ฑดฐด\nโุจุฏูู ูฺ ูุฒูู ุงุถุงู ูุณุชูู ุงุฒ ููุงูุฏฺฏ \nโ๏ธูุทูุง ุชูุฌู ฺฉูุฏ :\nุงู ุฎูุฏุฑู ูุฏู ฑดฐด ูุฏุงุฑุฏ ู ููุท ูุฏุงุฑฺฉ ุฏุฑุณุงู ฑดฐด ุตุงุฏุฑ ุดุฏู โ๏ธ",
    "ฺฉุงุฑฺฉุฑุฏ": "ุตูุฑ ฺฉูููุชุฑ",
    "ููุน ุณูุฎุช": "ุจูุฒู",
    "ฺฏุฑุจฺฉุณ": "ุงุชููุงุชฺฉ",
    "ูุถุนุช ุจุฏูู": "ุจุฏูู ุฑูฺฏ",
    "ุฑูฺฏ ุจุฏูู": "ุณูุฏ",
    "ุฑูฺฏ ุฏุงุฎู": "ุฏุงุฎู ูุดฺฉ",
    "ุญุฌู ููุชูุฑ": "1.6 ูุชุฑ",
    "ูพุดุฑุงูู": "4 ุณููุฏุฑ",
    "ุดุชุงุจ": "10.8 ุซุงูู",
    "ูุตุฑู ุชุฑฺฉุจ": "7.6 ูุชุฑ ุฏุฑ ุตุฏ ฺฉูููุชุฑ"
  },
  {
    "ูุงู": "ฺฉ ุงู ุณุ ุงฺฏู",
    "ุณุงู ุณุงุฎุช": "1404",
    "ูุฏู": "1.5 ูุชุฑ",
    "ุชุงู": "ุฏูุงู ูพุด",
    "ููุช": 1050000000.0,
    "ุขุฏุฑุณ": "ุชูุฑุงู / ุตุฏุฑ",
    "ุชูุถุญุงุช": " ุชูุถุญุงุช ๐ฉููุงูุฏฺฏ ูุฌุงุฒ ฺฉุฑูุงู ููุชูุฑ ฺฉุฏ 314ุฑูุน๐ฉ\nโฎ๏ธ ุชุญูู 20ุฑูุฒ ฺฉุงุฑ ู ุชุญูู ุฏุฑุจ ฺฉุงุฑุฎุงูู \nโฎ๏ธ ุณูุฏ ุฏุณุชู ุงูู ุจู ูุงู ุดูุง ุฎุฑุฏุงุฑ ูุญุชุฑู \nูุฒุงุง :\nโุตุฑูู ุฌู ุฏุฑ ุฒูุงู ู ูุฒูู\nโุจุฏูู ูุงุณุทู ุูุณุชูู ุงุฒ ูุฑูุดูุฏู\nโุฎุฑุฏ ูุทูุฆู ู ุจุฏูู ุฏุฑุฏุณุฑ\nโุฌูุช ฺฉุณุจ ุงุทูุงุนุงุช ุจุดุชุฑ ุจุงููฺฉุงุฑุงู ูุง ุฏุฑ ุงุฑุชุจุงุท ุจุงุดุฏ",
    "ฺฉุงุฑฺฉุฑุฏ": "ุตูุฑ ฺฉูููุชุฑ",
    "ููุน ุณูุฎุช": "ุจูุฒู",
    "ฺฏุฑุจฺฉุณ": "ุงุชููุงุชฺฉ",
    "ูุถุนุช ุจุฏูู": "ุจุฏูู ุฑูฺฏ",
    "ุฑูฺฏ ุจุฏูู": "ุฎุงฺฉุณุชุฑ",
    "ุฑูฺฏ ุฏุงุฎู": "ุฏุงุฎู ุฎุงฺฉุณุชุฑ",
    "ุญุฌู ููุชูุฑ": "1.5 ูุชุฑ",
    "ูพุดุฑุงูู": "4 ุณููุฏุฑ",
    "ุดุชุงุจ": "12.5 ุซุงูู",
    "ูุตุฑู ุชุฑฺฉุจ": "6.8 ูุชุฑ ุฏุฑ ุตุฏ ฺฉูููุชุฑ"
  },
  {
    "ูุงู": "ูููฺฉุณุ ID.4 Crozz",
    "ุณุงู ุณุงุฎุช": "2024",
    "ูุฏู": "PURE",
    "ุชุงู": "ุฏูุงู ูพุด",
    "ููุช": "ุชูุงูู",
    "ุขุฏุฑุณ": "ุชูุฑุงู / ุขุฌูุฏุงูู",
    "ุชูุถุญุงุช": " ุชูุถุญุงุช โ๏ธููุงูุฏฺฏ ุฑุณู ูุงููุช ุฎูุฏุฑู\nโ๏ธูพุฑูุฑูุด ุชุฑู ุฎูุฏุฑู ุจุฑู\nโ๏ธููุช ุจุงูุฑูฺฉุฑุฏู\nโ๏ธูุงูุชูุฑ ุจุฒุฑฺฏ\nโ๏ธููุฏ ู ุงูุณุงุท\nโ๏ธุดุฑุงุท ูุฑูุด ุนุงู\nโ๏ธุฎุฑุฏ ุฑุงุญุช ู ุขุณูุฏู\n๐จโ๐ผฺฉุงุฑุดูุงุณ ูุฑูุด \nูุตุทู ูุดูุฏ",
    "ฺฉุงุฑฺฉุฑุฏ": "ุตูุฑ ฺฉูููุชุฑ",
    "ููุน ุณูุฎุช": "ุจุฑู",
    "ฺฏุฑุจฺฉุณ": "ุงุชููุงุชฺฉ",
    "ูุถุนุช ุจุฏูู": "ุจุฏูู ุฑูฺฏ",
    "ุฑูฺฏ ุจุฏูู": "ุณุฑูู ุง",
    "ุฑูฺฏ ุฏุงุฎู": "ุฏุงุฎู ูุดฺฉ",
    "ูพุดุฑุงูู": "1 ููุชูุฑ ุงูฺฉุชุฑฺฉ",
    "ุดุชุงุจ": "9 ุซุงูู"
  },
  {
    "ูุงู": "ฺฉ ุงู ุณุ T8",
    "ุณุงู ุณุงุฎุช": "1404",
    "ูุฏู": "ุฏูุฏู ุง",
    "ุชุงู": "ุฏูุงู ูพุด",
    "ููุช": 1010000000.0,
    "ุขุฏุฑุณ": "ุชูุฑุงู / ูพููฺฉ",
    "ุชูุถุญุงุช": " ุชูุถุญุงุช ููุงูุฏฺฏ ูุฌุงุฒ ฺฉุฑูุงู ููุชูุฑ ฺฉุฏ 1752 ุฑูุน \n ุซุจุช ูุงู ููุฏ ู ุงูุณุงุท \n ุงูุณุงุท 12 ุงู 24 ูุงูู\n ุชุญูู 90 ุฑูุฒฺฉุงุฑ \n------------------------------------------\nุฌูุช ฺฉุณุจ ุงุทูุงุนุงุช ุจุดุชุฑ ุจุง ููฺฉุงุฑุงู ูุง ุฏุฑ ุงุฑุชุจุงุท ุจุงุดุฏ .",
    "ฺฉุงุฑฺฉุฑุฏ": "ุตูุฑ ฺฉูููุชุฑ",
    "ููุน ุณูุฎุช": "ุจูุฒู",
    "ฺฏุฑุจฺฉุณ": "ุฏูุฏู ุง",
    "ูุถุนุช ุจุฏูู": "ุจุฏูู ุฑูฺฏ",
    "ุฑูฺฏ ุจุฏูู": "ูุฑูุฒ",
    "ุฑูฺฏ ุฏุงุฎู": "ุฏุงุฎู ูุดฺฉ"
  },
  {
    "ูุงู": "ูููฺฉุณุ ุช ุฑุงฺฉ",
    "ุณุงู ุณุงุฎุช": "2024",
    "ูุฏู": "1.5 ูุชุฑ ุชูุฑุจู",
    "ุชุงู": "ุฏูุงู ูพุด",
    "ููุช": "ุชูุงูู",
    "ุขุฏุฑุณ": "ุชูุฑุงู / ุขุฌูุฏุงูู",
    "ุชูุถุญุงุช": " ุชูุถุญุงุช โ๏ธูพูุงฺฉ ุขูุงุฏู ุชุญูู\nโ๏ธููุฏ ูุงูุณุงุท\nโ๏ธุฎุฏูุงุช VIP\nโ๏ธุจู ููุฑุงู ฺฉุงุฑุดูุงุณ\nโ๏ธุฎุฑุฏ ุงูู ู ุฑุงุญุช\nโ๏ธุทุฑุญ ุชุนูุถ ุฎูุฏุฑู ูุง ฺฉุงุฑฺฉุฑุฏู\nโ๏ธููุงูุฏฺฏ ุฑุณู ูุงููุช ุฎูุฏุฑู\nโ๏ธฺฉุงุฑุดูุงุณ ูุฑูุด \nโ๏ธูุตุทู ูุดูุฏ",
    "ฺฉุงุฑฺฉุฑุฏ": "ุตูุฑ ฺฉูููุชุฑ",
    "ููุน ุณูุฎุช": "ุจูุฒู",
    "ฺฏุฑุจฺฉุณ": "ุงุชููุงุชฺฉ",
    "ูุถุนุช ุจุฏูู": "ุจุฏูู ุฑูฺฏ",
    "ุฑูฺฏ ุจุฏูู": "ุณูุฏ",
    "ุฑูฺฏ ุฏุงุฎู": "ุฏุงุฎู ูุดฺฉ",
    "ุญุฌู ููุชูุฑ": "1.5 ูุชุฑ",
    "ูพุดุฑุงูู": "4 ุณููุฏุฑ ุชูุฑุจูุดุงุฑฺ (EA211)",
    "ุดุชุงุจ": "9.4 ุซุงูู",
    "ูุตุฑู ุชุฑฺฉุจ": "6.1 ูุชุฑ ุฏุฑ ุตุฏ ฺฉูููุชุฑ"
  },
  {
    "ูุงู": "ฺฉูฺฉุ GX",
    "ุณุงู ุณุงุฎุช": "1403",
    "ูุฏู": "L ุฏูุฏู ุง",
    "ุชุงู": "ุฏูุงู ูพุด",
    "ููุช": 485000000.0,
    "ุขุฏุฑุณ": "ุชูุฑุงู / ุดูุฑุขุฑุง",
    "ุชูุถุญุงุช": " ุชูุถุญุงุช ุจุง ุชุฑูุฒ ESC ุฏุฑ ุญุฏ ุตูุฑ",
    "ฺฉุงุฑฺฉุฑุฏ": "1,700 km",
    "ููุน ุณูุฎุช": "ุจูุฒู",
    "ฺฏุฑุจฺฉุณ": "ุฏูุฏู ุง",
    "ูุถุนุช ุจุฏูู": "ุจุฏูู ุฑูฺฏ",
    "ุฑูฺฏ ุจุฏูู": "ุณูุฏ",
    "ุฑูฺฏ ุฏุงุฎู": "ุฏุงุฎู ูุดฺฉ",
    "ุญุฌู ููุชูุฑ": "1.5 ูุชุฑ",
    "ูพุดุฑุงูู": "4 ุณููุฏุฑ M15i ุจูุจูุฏุงูุชู",
    "ูุตุฑู ุชุฑฺฉุจ": "6.7 ูุชุฑ ุฏุฑ ุตุฏ ฺฉูููุชุฑ"
  },
  {
    "ูุงู": "ูููุฏุงุ ฺฉููุง",
    "ุณุงู ุณุงุฎุช": "2025",
    "ูุฏู": "2.0 ูุชุฑ",
    "ุชุงู": "ุฏูุงู ูพุด",
    "ููุช": 2500000000.0,
    "ุขุฏุฑุณ": "ุชูุฑุงู / ุตุฏุฑ",
    "ุชูุถุญุงุช": " ุชูุถุญุงุช ุชูุถุญุงุช\n_ููุงูุฏฺฏ ูุฌุงุฒ ูููุฏุง ฺฉุฏ 314 ูุทุฑู \nโ๏ธููุฏูุงูุณุงุท\nโ๏ธ ุจุฏูู ุถุงูู\nโ๏ธุณูุฏุจูุงู ุฎุฑุฏุงุฑ\nโ๏ธุชุญูู ถฐ ุฑูุฒโฺฉุงุฑ\nโ๏ธููุนุฏ ฺฺฉ ูุฑณ ูุงู\n_________________________\nุซุจุช ูุงู ุงูุณุงุท\nุงูุณุงุท ุจู ุตูุฑุช ุณู ูุงู ู ุจุงุฑ ู ุชุงุฑุฎ ุงููู ฺฺฉ 15ุงุจุงู",
    "ฺฉุงุฑฺฉุฑุฏ": "ุตูุฑ ฺฉูููุชุฑ",
    "ููุน ุณูุฎุช": "ุจูุฒู",
    "ฺฏุฑุจฺฉุณ": "ุงุชููุงุชฺฉ",
    "ูุถุนุช ุจุฏูู": "ุจุฏูู ุฑูฺฏ",
    "ุฑูฺฏ ุจุฏูู": "ูุดฺฉ",
    "ุฑูฺฏ ุฏุงุฎู": "ุฏุงุฎู ูุดฺฉ",
    "ุญุฌู ููุชูุฑ": "2.0 ูุชุฑ",
    "ูพุดุฑุงูู": "4 ุณููุฏุฑ MPi",
    "ุดุชุงุจ": "10.8 ุซุงูู",
    "ูุตุฑู ุชุฑฺฉุจ": "7.3 ูุชุฑ ุฏุฑ ุตุฏ ฺฉูููุชุฑ"
  },
  {
    "ูุงู": "ุฏฺฏูุชุ ูพุฑุงู",
    "ุณุงู ุณุงุฎุช": "1404",
    "ูุฏู": "ุงุชููุงุชฺฉ",
    "ุชุงู": "ุฏูุงู ูพุด",
    "ููุช": 1995000000.0,
    "ุขุฏุฑุณ": "ุชูุฑุงู / ุดูุฑฺฉ ุฑุงูโุขูู",
    "ุชูุถุญุงุช": " ุชูุถุญุงุช ููุฏ ู ุงูุณุงุท ุุจู ุดุฑุท ฺฉุงุฑุดูุงุณ ุุจู ุดุฑุท ุฑูุชุุณูุฏ ุงุฒุงุฏุูุนุงูุถู ุจุง ุฎูุฏุฑู ุดูุง\nุดุฌุฑ",
    "ฺฉุงุฑฺฉุฑุฏ": "ุตูุฑ ฺฉูููุชุฑ",
    "ููุน ุณูุฎุช": "ุจูุฒู",
    "ฺฏุฑุจฺฉุณ": "ุงุชููุงุชฺฉ",
    "ูุถุนุช ุจุฏูู": "ุจุฏูู ุฑูฺฏ",
    "ุฑูฺฏ ุจุฏูู": "ุณูุฏ",
    "ุฑูฺฏ ุฏุงุฎู": "ุฏุงุฎู ูุดฺฉ",
    "ุญุฌู ููุชูุฑ": "1.5 ูุชุฑ",
    "ูพุดุฑุงูู": "4 ุณููุฏุฑ ุชูุฑุจูุดุงุฑฺ (SFG15T)",
    "ุดุชุงุจ": "13 ุซุงูู",
    "ูุตุฑู ุชุฑฺฉุจ": "7.3 ูุชุฑ ุฏุฑ ุตุฏ ฺฉูููุชุฑ"
  },
  {
    "ูุงู": "ฺฉ ุงู ุณุ T8",
    "ุณุงู ุณุงุฎุช": "1404",
    "ูุฏู": "ุฏูุฏู ุง",
    "ุชุงู": "ุฏูุงู ูพุด",
    "ููุช": 2110000000.0,
    "ุขุฏุฑุณ": "ุชูุฑุงู / ุตุฏุฑ",
    "ุชูุถุญุงุช": " ุชูุถุญุงุช ๐ฉููุงูุฏฺฏ ูุฌุงุฒ ฺฉุฑูุงู ููุชูุฑ ฺฉุฏ 314 ุฑูุน๐ฉ\nโุฌูุช ฺฉุณุจ ุงุทูุงุนุงุช ุจุดุชุฑ ุจุงููฺฉุงุฑุงู ูุง ุฏุฑ ุงุฑุชุจุงุท ุจุงุดุฏ",
    "ฺฉุงุฑฺฉุฑุฏ": "ุตูุฑ ฺฉูููุชุฑ",
    "ููุน ุณูุฎุช": "ุจูุฒู",
    "ฺฏุฑุจฺฉุณ": "ุฏูุฏู ุง",
    "ูุถุนุช ุจุฏูู": "ุจุฏูู ุฑูฺฏ",
    "ุฑูฺฏ ุจุฏูู": "ูุดฺฉ",
    "ุฑูฺฏ ุฏุงุฎู": "ุฏุงุฎู ูุดฺฉ"
  },
  {
    "ูุงู": "ูููุฏุงุ ฺฉููุง",
    "ุณุงู ุณุงุฎุช": "2025",
    "ูุฏู": "2.0 ูุชุฑ",
    "ุชุงู": "ุฏูุงู ูพุด",
    "ููุช": 2500000000.0,
    "ุขุฏุฑุณ": "ุชูุฑุงู / ูพููฺฉ",
    "ุชูุถุญุงุช": " ุชูุถุญุงุช โููุงูุฏฺฏ ูุฌุงุฒ ฺฉุฑูุงู ููุชูุฑ ฺฉุฏ 1752 ุฑูุน โ\nโฆุซุจุช ูุงู ููุฏ ู ุงูุณุงุท \nโฆุงูุณุงุท ุจู ุตูุฑุช ูุฑ ุณู ูุงู ฺฉ ุจุงุฑ ู ุชุงุฑุฎ ุงููู ฺฺฉ1404 /08 /15\nโุฌูุช ฺฉุณุจ ุงุทูุงุนุงุช ุจุดุชุฑ ุชูุงุณ ุจฺฏุฑุฏ.",
    "ฺฉุงุฑฺฉุฑุฏ": "ุตูุฑ ฺฉูููุชุฑ",
    "ููุน ุณูุฎุช": "ุจูุฒู",
    "ฺฏุฑุจฺฉุณ": "ุงุชููุงุชฺฉ",
    "ูุถุนุช ุจุฏูู": "ุจุฏูู ุฑูฺฏ",
    "ุฑูฺฏ ุจุฏูู": "ูุดฺฉ",
    "ุฑูฺฏ ุฏุงุฎู": "ุฏุงุฎู ูุดฺฉ",
    "ุญุฌู ููุชูุฑ": "2.0 ูุชุฑ",
    "ูพุดุฑุงูู": "4 ุณููุฏุฑ MPi",
    "ุดุชุงุจ": "10.8 ุซุงูู",
    "ูุตุฑู ุชุฑฺฉุจ": "7.3 ูุชุฑ ุฏุฑ ุตุฏ ฺฉูููุชุฑ"
  },
  {
    "ูุงู": "ฺฉ ุงู ุณุ T9",
    "ุณุงู ุณุงุฎุช": "1404",
    "ูุฏู": "2 ูุชุฑ ุชูุฑุจู",
    "ุชุงู": "ุฏูุงู ูพุด",
    "ููุช": 2750000000.0,
    "ุขุฏุฑุณ": "ุชูุฑุงู / ูพููฺฉ",
    "ุชูุถุญุงุช": " ุชูุถุญุงุช ^^^^^^^^ููุงูุฏฺฏ ูุฌุงุฒ ฺฉุฑูุงู ููุชูุฑ ฺฉุฏ 1752 ุฑูุน^^^^^^^^\nโฎ๏ธ ุชุญูู 20ุฑูุฒ ฺฉุงุฑ ู ุชุญูู ุฏุฑุจ ฺฉุงุฑุฎุงูู \nโฎ๏ธ ุณูุฏ ุฏุณุชู ุงูู ุจู ูุงู ุดูุง ุฎุฑุฏุงุฑ ูุญุชุฑู \nูุฒุงุง :\nโุตุฑูู ุฌู ุฏุฑ ุฒูุงู ู ูุฒูู\nโุจุฏูู ูุงุณุทู ุูุณุชูู ุงุฒ ูุฑูุดูุฏู\nโุฎุฑุฏ ูุทูุฆู ู ุจุฏูู ุฏุฑุฏุณุฑ\nโุฌูุช ฺฉุณุจ ุงุทูุงุนุงุช ุจุดุชุฑ ุจุงููฺฉุงุฑุงู ูุง ุฏุฑ ุงุฑุชุจุงุท ุจุงุดุฏ",
    "ฺฉุงุฑฺฉุฑุฏ": "ุตูุฑ ฺฉูููุชุฑ",
    "ููุน ุณูุฎุช": "ุจูุฒู",
    "ฺฏุฑุจฺฉุณ": "ุงุชููุงุชฺฉ",
    "ูุถุนุช ุจุฏูู": "ุจุฏูู ุฑูฺฏ",
    "ุฑูฺฏ ุจุฏูู": "ูุดฺฉ",
    "ุฑูฺฏ ุฏุงุฎู": "ุฏุงุฎู ูุดฺฉ",
    "ุญุฌู ููุชูุฑ": "2.0 ูุชุฑ",
    "ูพุดุฑุงูู": "4 ุณููุฏุฑ ุชูุฑุจูุดุงุฑฺ (HFC4DB2)"
  },
  {
    "ูุงู": "ูููฺฉุณุ ุชฺฏู 8 ูพุฑู ูฺฉุณ",
    "ุณุงู ุณุงุฎุช": "1404",
    "ูุฏู": "IE",
    "ุชุงู": "ุฏูุงู ูพุด",
    "ููุช": 3695000000.0,
    "ุขุฏุฑุณ": "ุชูุฑุงู / ุดูุฑฺฉ ุฑุงูโุขูู",
    "ุชูุถุญุงุช": " ุชูุถุญุงุช ุชุญูู ููุฑ\nุจู ุดุฑุท ฺฉุงุฑุดูุงุณ\nุจุฎุชุงุฑ",
    "ฺฉุงุฑฺฉุฑุฏ": "ุตูุฑ ฺฉูููุชุฑ",
    "ููุน ุณูุฎุช": "ุจูุฒู",
    "ฺฏุฑุจฺฉุณ": "ุงุชููุงุชฺฉ",
    "ูุถุนุช ุจุฏูู": "ุจุฏูู ุฑูฺฏ",
    "ุฑูฺฏ ุจุฏูู": "ุณูุฏ",
    "ุฑูฺฏ ุฏุงุฎู": "ุฏุงุฎู ููฺฉุง",
    "ุญุฌู ููุชูุฑ": "2.0 ูุชุฑ",
    "ูพุดุฑุงูู": "4 ุณููุฏุฑ ุชูุฑุจูุดุงุฑฺ (4J20)",
    "ุดุชุงุจ": "8.1 ุซุงูู",
    "ูุตุฑู ุชุฑฺฉุจ": "7.9 ูุชุฑ ุฏุฑ ุตุฏ ฺฉูููุชุฑ"
  },
  {
    "ูุงู": "ุฌฺฉุ ุฌ 4",
    "ุณุงู ุณุงุฎุช": "1404",
    "ูุฏู": "ุงุชููุงุชฺฉ",
    "ุชุงู": "ุฏูุงู ูพุด",
    "ููุช": 1050000000.0,
    "ุขุฏุฑุณ": "ุชูุฑุงู / ุตุฏุฑ",
    "ุชูุถุญุงุช": " ุชูุถุญุงุช ุชูุถุญุงุช\nโญ ููุงูุฏฺฏ ูุฌุงุฒ ฺฉุฑูุงู ููุชูุฑ ฺฉุฏ 314 ุฑูุน ูุงโญ\nโญ ูุฑูุด ููุฏ\nโ๏ธุชุญูู ููุฑ\nโ๏ธุฎุฑุฏ ุนุงู ู ูุทูุฆู",
    "ฺฉุงุฑฺฉุฑุฏ": "ุตูุฑ ฺฉูููุชุฑ",
    "ููุน ุณูุฎุช": "ุจูุฒู",
    "ฺฏุฑุจฺฉุณ": "ุงุชููุงุชฺฉ",
    "ูุถุนุช ุจุฏูู": "ุจุฏูู ุฑูฺฏ",
    "ุฑูฺฏ ุจุฏูู": "ุณูุฏ",
    "ุฑูฺฏ ุฏุงุฎู": "ุฏุงุฎู ูุดฺฉ",
    "ุญุฌู ููุชูุฑ": "1.5 ูุชุฑ",
    "ูพุดุฑุงูู": "4 ุณููุฏุฑ",
    "ุดุชุงุจ": "11 ุซุงูู",
    "ูุตุฑู ุชุฑฺฉุจ": "6.2 ูุชุฑ ุฏุฑ ุตุฏ ฺฉูููุชุฑ"
  },
  {
    "ูุงู": "ุงู ู ุงูุ X33 ฺฉุฑุงุณ",
    "ุณุงู ุณุงุฎุช": "1403",
    "ูุฏู": "ุฏูุฏู ุง",
    "ุชุงู": "ุฏูุงู ูพุด",
    "ููุช": 1220000000.0,
    "ุขุฏุฑุณ": "ุชูุฑุงู / ุดูุฏ ูุทูุฑ",
    "ุชูุถุญุงุช": " ุชูุถุญุงุช ----- ฺู ููุฏ -----\nโ ูุดุงูุฑ ู ฺฉุงุฑุดูุงุณ ุดูุง : ุฎุงูู ุฌุงูุฏ\nโฝ๏ธ ๏ธุชุญูู ุจู ุฑูุฒ ุจุง ุณูุฏ ู ูุฏุงุฑฺฉ ุขูุงุฏู .\nโฝ๏ธ๏ธ ุฎูุฏุฑู  ุฎุดฺฉ ุูุงุจู ุฑูุช ุญุถูุฑ .\nโฝ๏ธ๏ธ ุญู ฺฉุงุฑุดูุงุณ ูุจู ุงุฒ ุฎุฑุฏ ุจุง ุดูุง .\nโฝ ๏ธ ุชูุงู ุฎูุฏุฑููุง ุฏุงุฑุง ฺฏุงุฑุงูุช ูุนุงู ู ุจูู ูุงูู ูุจุงุดุฏ .\n๏ธโ ูุงุจู ูุนุงูุถู ",
    "ฺฉุงุฑฺฉุฑุฏ": "ุตูุฑ ฺฉูููุชุฑ",
    "ููุน ุณูุฎุช": "ุจูุฒู",
    "ฺฏุฑุจฺฉุณ": "ุฏูุฏู ุง",
    "ูุถุนุช ุจุฏูู": "ุจุฏูู ุฑูฺฏ",
    "ุฑูฺฏ ุจุฏูู": "ูุดฺฉ",
    "ุฑูฺฏ ุฏุงุฎู": "ุฏุงุฎู ูุดฺฉ"
  },
  {
    "ูุงู": "ุฑุณูพฺฉุชุ ูพุฑุงู",
    "ุณุงู ุณุงุฎุช": "1404",
    "ูุฏู": "ุชูพ 2",
    "ุชุงู": "ุฏูุงู ูพุด",
    "ููุช": "ุชูุงูู",
    "ุขุฏุฑุณ": "ุชูุฑุงู / ุงูุฏุฑุฒฺฏู",
    "ุชูุถุญุงุช": " ุชูุถุญุงุช โุงูุฏ ฺฏุงูุฑ\nุจุด ุงุฒ ฑต ุณุงู ุณุงุจูู ุฏุฑ ุฎุฑุฏ ู ูุฑูุด ูุงุดู\nุนุถู ุฑุณู ุงุชุญุงุฏู\nุชุญูู ููุฑ ุจุง ุงูฺฉุงู ฺฉุงุฑุดูุงุณ\nโููุช ุขุฎุฑ ุฑุง ุงุฒ ูุง ุจุฎูุงูุฏ",
    "ฺฉุงุฑฺฉุฑุฏ": "ุตูุฑ ฺฉูููุชุฑ",
    "ููุน ุณูุฎุช": "ุจูุฒู",
    "ฺฏุฑุจฺฉุณ": "ุงุชููุงุชฺฉ",
    "ูุถุนุช ุจุฏูู": "ุจุฏูู ุฑูฺฏ",
    "ุฑูฺฏ ุจุฏูู": "ุณูุฏ",
    "ุฑูฺฏ ุฏุงุฎู": "ุฏุงุฎู ูุดฺฉ",
    "ุญุฌู ููุชูุฑ": "1.5 ูุชุฑ",
    "ูพุดุฑุงูู": "4 ุณููุฏุฑ ุชูุฑุจูุดุงุฑฺ (4T15C)",
    "ุดุชุงุจ": "10.5 ุซุงูู",
    "ูุตุฑู ุชุฑฺฉุจ": "7.5 ูุชุฑ ุฏุฑ ุตุฏ ฺฉูููุชุฑ"
  },
  {
    "ูุงู": "ฺุงูฺฏุงูุ CS 55 ูพูุงุณ",
    "ุณุงู ุณุงุฎุช": "2024",
    "ูุฏู": "1.5 ูุชุฑ ุชูุฑุจู",
    "ุชุงู": "ุฏูุงู ูพุด",
    "ููุช": "ุชูุงูู",
    "ุขุฏุฑุณ": "ุชูุฑุงู / ูุงูุฑุงู",
    "ุชูุถุญุงุช": " ุชูุถุญุงุช โญ๏ธโฺฉุงุฑุดูุงุณ ุฎูุฏุฑู ุฎุงูู ุณุนุงุฏุชโ\nโญ๏ธโูุฑูุด ุชุฎุตุต ุฎูุฏุฑููุง ูููุชุงฺ ู ูุงุฑุฏุงุช ุงูุณุงุทโ\nโุงูุณุงุท ููุท ุจุง ฺฺฉ ุตุงุฏ.ุชูุฑุงู ู ุดูุฑุณุชุงู\nโูุฑูุด ุฎูุฏุฑู ูููุชุงฺ ู ูุงุฑุฏุงุช ุจู ุตูุฑุช ููุฏู ุงูุณุงุทโ\n๏ธโุฎูุฏุฑููุง ูพูุงฺฉ ุดุฏู ุณูุฏ ุขุฒุงุฏโ\nโณุณุงุนุช ูุฑุงุฌุนู: 8:30 ุงู 17โ\nโจุชุญูู ููุฑโ\nโ**ุฎุงูู ุณุนุงุฏุช**โ",
    "ฺฉุงุฑฺฉุฑุฏ": "ุตูุฑ ฺฉูููุชุฑ",
    "ููุน ุณูุฎุช": "ุจูุฒู",
    "ฺฏุฑุจฺฉุณ": "ุงุชููุงุชฺฉ",
    "ูุถุนุช ุจุฏูู": "ุจุฏูู ุฑูฺฏ",
    "ุฑูฺฏ ุจุฏูู": "ูุดฺฉ",
    "ุฑูฺฏ ุฏุงุฎู": "ุฏุงุฎู ูุดฺฉ",
    "ุญุฌู ููุชูุฑ": "1.5 ูุชุฑ",
    "ูพุดุฑุงูู": "4 ุณููุฏุฑ ุชูุฑุจูุดุงุฑฺ (JL473ZQ7)",
    "ูุตุฑู ุชุฑฺฉุจ": "6.6 ูุชุฑ ุฏุฑ ุตุฏ ฺฉูููุชุฑ"
  },
  {
    "ูุงู": "ุฑุณูพฺฉุชุ ูพุฑุงู",
    "ุณุงู ุณุงุฎุช": "1404",
    "ูุฏู": "ุชูพ 2",
    "ุชุงู": "ุฏูุงู ูพุด",
    "ููุช": 1810000000.0,
    "ุขุฏุฑุณ": "ุชูุฑุงู / ุดูุฏ ูุทูุฑ",
    "ุชูุถุญุงุช": " ุชูุถุญุงุช ----- ฺู ููุฏ -----\nูุดุงูุฑ ู ฺฉุงุฑุดูุงุณ ุดูุง :ุขูุง ูุนู\nโ๏ธุชุญูู ุจู ุฑูุฒ ุจุง ุณูุฏ ู ูุฏุงุฑฺฉ ุขูุงุฏู\nโ๏ธุฎูุฏุฑู ุฎุดฺฉ ุูุงุจู ุฑูุช ุญุถูุฑ\nโ๏ธุญู ฺฉุงุฑุดูุงุณ ูุจู ุงุฒ ุฎุฑุฏ ุจุง ุดูุง\nโ๏ธ ุชูุงู ุฎูุฏุฑููุง ุฏุงุฑุง ฺฏุงุฑุงูุช ูุนุงู ู ุจูู ูุงูู ูุจุงุดุฏ.\nโ๏ธูุงุจู ูุนุงูุถู ",
    "ฺฉุงุฑฺฉุฑุฏ": "ุตูุฑ ฺฉูููุชุฑ",
    "ููุน ุณูุฎุช": "ุจูุฒู",
    "ฺฏุฑุจฺฉุณ": "ุงุชููุงุชฺฉ",
    "ูุถุนุช ุจุฏูู": "ุจุฏูู ุฑูฺฏ",
    "ุฑูฺฏ ุจุฏูู": "ูุดฺฉ",
    "ุฑูฺฏ ุฏุงุฎู": "ุฏุงุฎู ูุดฺฉ",
    "ุญุฌู ููุชูุฑ": "1.5 ูุชุฑ",
    "ูพุดุฑุงูู": "4 ุณููุฏุฑ ุชูุฑุจูุดุงุฑฺ (4T15C)",
    "ุดุชุงุจ": "10.5 ุซุงูู",
    "ูุตุฑู ุชุฑฺฉุจ": "7.5 ูุชุฑ ุฏุฑ ุตุฏ ฺฉูููุชุฑ"
  },
  {
    "ูุงู": "ฺฉ ุงู ุณุ X5",
    "ุณุงู ุณุงุฎุช": "1404",
    "ูุฏู": "1.5 ูุชุฑ ุชูุฑุจู",
    "ุชุงู": "ุฏูุงู ูพุด",
    "ููุช": 1890000000.0,
    "ุขุฏุฑุณ": "ุชูุฑุงู / ุตุฏุฑ",
    "ุชูุถุญุงุช": " ุชูุถุญุงุช ๐ฉููุงูุฏฺฏ ูุฌุงุฒ ฺฉุฑูุงู ููุชูุฑ ฺฉุฏ 314 ุฑูุน๐ฉ\nโฎ๏ธ ุชุญูู 20ุฑูุฒ ฺฉุงุฑ ู ุชุญูู ุฏุฑุจ ฺฉุงุฑุฎุงูู \nโฎ๏ธ ุณูุฏ ุฏุณุชู ุงูู ุจู ูุงู ุดูุง ุฎุฑุฏุงุฑ ูุญุชุฑู \nูุฒุงุง :\nโุตุฑูู ุฌู ุฏุฑ ุฒูุงู ู ูุฒูู\nโุจุฏูู ูุงุณุทู ุูุณุชูู ุงุฒ ูุฑูุดูุฏู\nโุฎุฑุฏ ูุทูุฆู ู ุจุฏูู ุฏุฑุฏุณุฑ\nโุฌูุช ฺฉุณุจ ุงุทูุงุนุงุช ุจุดุชุฑ ุจุงููฺฉุงุฑุงู ูุง ุฏุฑ ุงุฑุชุจุงุท ุจุงุดุฏ",
    "ฺฉุงุฑฺฉุฑุฏ": "ุตูุฑ ฺฉูููุชุฑ",
    "ููุน ุณูุฎุช": "ุจูุฒู",
    "ฺฏุฑุจฺฉุณ": "ุงุชููุงุชฺฉ",
    "ูุถุนุช ุจุฏูู": "ุจุฏูู ุฑูฺฏ",
    "ุฑูฺฏ ุจุฏูู": "ุณูุฏ",
    "ุฑูฺฏ ุฏุงุฎู": "ุฏุงุฎู ูุดฺฉ",
    "ุญุฌู ููุชูุฑ": "1.5 ูุชุฑ",
    "ูพุดุฑุงูู": "4 ุณููุฏุฑ ุชูุฑุจูุดุงุฑฺ (4GC16D)"
  },
  {
    "ูุงู": "ฺฉ ุงู ุณุ J7",
    "ุณุงู ุณุงุฎุช": "1404",
    "ูุฏู": "ุงุชููุงุชฺฉ",
    "ุชุงู": "ุฏูุงู ูพุด",
    "ููุช": 1840000000.0,
    "ุขุฏุฑุณ": "ุชูุฑุงู / ูพููฺฉ",
    "ุชูุถุญุงุช": " ุชูุถุญุงุช ^^^^^^^^ููุงูุฏฺฏ ูุฌุงุฒ ฺฉุฑูุงู ููุชูุฑ ฺฉุฏ 1752 ุฑูุน^^^^^^^^\nโฎ๏ธ ุชุญูู 20ุฑูุฒ ฺฉุงุฑ ู ุชุญูู ุฏุฑุจ ฺฉุงุฑุฎุงูู \nโฎ๏ธ ุณูุฏ ุฏุณุชู ุงูู ุจู ูุงู ุดูุง ุฎุฑุฏุงุฑ ูุญุชุฑู \nูุฒุงุง :\nโุตุฑูู ุฌู ุฏุฑ ุฒูุงู ู ูุฒูู\nโุจุฏูู ูุงุณุทู ุูุณุชูู ุงุฒ ูุฑูุดูุฏู\nโุฎุฑุฏ ูุทูุฆู ู ุจุฏูู ุฏุฑุฏุณุฑ\nโุฌูุช ฺฉุณุจ ุงุทูุงุนุงุช ุจุดุชุฑ ุจุงููฺฉุงุฑุงู ูุง ุฏุฑ ุงุฑุชุจุงุท ุจุงุดุฏ",
    "ฺฉุงุฑฺฉุฑุฏ": "ุตูุฑ ฺฉูููุชุฑ",
    "ููุน ุณูุฎุช": "ุจูุฒู",
    "ฺฏุฑุจฺฉุณ": "ุงุชููุงุชฺฉ",
    "ูุถุนุช ุจุฏูู": "ุจุฏูู ุฑูฺฏ",
    "ุฑูฺฏ ุจุฏูู": "ูุดฺฉ",
    "ุฑูฺฏ ุฏุงุฎู": "ุฏุงุฎู ูุดฺฉ",
    "ุญุฌู ููุชูุฑ": "1.5 ูุชุฑ",
    "ูพุดุฑุงูู": "4 ุณููุฏุฑ ุชูุฑุจูุดุงุฑฺ TGDi"
  },
  {
    "ูุงู": "ูููฺฉุณุ ุชฺฏู 8 ูพุฑู ูฺฉุณ",
    "ุณุงู ุณุงุฎุช": "1402",
    "ูุฏู": "IE",
    "ุชุงู": "ุฏูุงู ูพุด",
    "ููุช": 3100000000.0,
    "ุขุฏุฑุณ": "ฺฉุฑุฌ / ุนุธูู",
    "ุชูุถุญุงุช": " ุชูุถุญุงุช  ุจุฏูู ุขุจุฑูฺฏ ู ูุณู\nฺฏุงุฑุงูุช ูุนุงู\nุณุฑูุณ ูุง ุฏูุฑู ุง ุจู ูููุน ุงูุฌุงูโ ุดุฏู ู ุณุฑูุณ ูุง ูุงู ุฏูุฑู ุง ูู ุฏุฑ ููุงูุฏฺฏ ุงูุฌุงู ุดุฏู\nููู ุชุฑู ูุณุฎู ุชฺฏู ธ ูพุฑููฺฉุณ ie\nูู ฺฉุงููุง ุณุงูู ู ุชูุงู ุขูพุดู ูุง ูุนุงู ูุจุงุดูุฏ",
    "ฺฉุงุฑฺฉุฑุฏ": "25,500 km",
    "ููุน ุณูุฎุช": "ุจูุฒู",
    "ฺฏุฑุจฺฉุณ": "ุงุชููุงุชฺฉ",
    "ูุถุนุช ุจุฏูู": "ุจุฏูู ุฑูฺฏ",
    "ุฑูฺฏ ุจุฏูู": "ุฎุงฺฉุณุชุฑ",
    "ุฑูฺฏ ุฏุงุฎู": "ุฏุงุฎู ููฺฉุง",
    "ุญุฌู ููุชูุฑ": "2.0 ูุชุฑ",
    "ูพุดุฑุงูู": "4 ุณููุฏุฑ ุชูุฑุจูุดุงุฑฺ (4J20)",
    "ุดุชุงุจ": "8.1 ุซุงูู",
    "ูุตุฑู ุชุฑฺฉุจ": "7.9 ูุชุฑ ุฏุฑ ุตุฏ ฺฉูููุชุฑ"
  },
  {
    "ูุงู": "ูููฺฉุณุ ุชฺฏู 8 ูพุฑู ูุจุฑุฏ",
    "ุณุงู ุณุงุฎุช": "1404",
    "ูุฏู": "e ูพูุงุณ",
    "ุชุงู": "ุฏูุงู ูพุด",
    "ููุช": "ุชูุงูู",
    "ุขุฏุฑุณ": "ุฑ / ุดูุฑุฑ ",
    "ุชูุถุญุงุช": " ุชูุถุญุงุช ููุงูุฏฺฏ ุงูุชุฎุงุฑ ฺฉุฏ 368 ุจุง ฺฉูุงู ุงุญุชุฑุงู ู ุงูุชุฎุงุฑ ุฏุฑ ุฎุฏูุช ุดูุงุณุช โุดุฑุงุท ุจู ุตูุฑุช ููุฏ ู ุงูุณุงุท ุจุง ฺฉูุชุฑู ุณูุฏ โุงุณุชูุงุฏู ุงุฒ ูพูุดุด ูฺู ุญูุงุช ุชุนูุฑฺฏุงู vip ูพุณ ุงุฒ ุฎุฑุฏ โฺฏุงุฑุงูุช ุฎูุฏุฑู 7 ุณุงูโุชุญูู ุฏุฑ ฺฉูุชุงู ุชุฑู ุฒูุงู โุฌูุช ุญูุธ ุณูุงูุช ูููุทูุงู ุนุฒุฒุุซุจุช ูุงู ุจู ุตูุฑุช ุบุฑ ุญุถูุฑ ูุฒ ุงูุฌุงู ูุดูุฏ",
    "ฺฉุงุฑฺฉุฑุฏ": "ุตูุฑ ฺฉูููุชุฑ",
    "ููุน ุณูุฎุช": "ูุจุฑุฏ",
    "ฺฏุฑุจฺฉุณ": "ุงุชููุงุชฺฉ",
    "ูุถุนุช ุจุฏูู": "ุจุฏูู ุฑูฺฏ",
    "ุฑูฺฏ ุจุฏูู": "ูุดฺฉ",
    "ุฑูฺฏ ุฏุงุฎู": "ุฏุงุฎู ูุดฺฉ",
    "ุญุฌู ููุชูุฑ": "1.5 ูุชุฑ",
    "ูพุดุฑุงูู": "4 ุณููุฏุฑ ุชูุฑุจูุดุงุฑฺ (4T15C) ุจุง 2 ููุชูุฑ ุงูฺฉุชุฑฺฉ",
    "ุดุชุงุจ": "7.6 ุซุงูู",
    "ูุตุฑู ุชุฑฺฉุจ": "6.5 ูุชุฑ ุฏุฑ ุตุฏ ฺฉูููุชุฑ"
  },
  {
    "ูุงู": "ฺฉ ุงู ุณุ J7",
    "ุณุงู ุณุงุฎุช": "1403",
    "ูุฏู": "ุงุชููุงุชฺฉ",
    "ุชุงู": "ุฏูุงู ูพุด",
    "ููุช": 1930000000.0,
    "ุขุฏุฑุณ": "ุชูุฑุงู / ุดูุฏ ูุทูุฑ",
    "ุชูุถุญุงุช": " ุชูุถุญุงุช ----- ฺู ููุฏ -----\nูุดุงูุฑ ู ฺฉุงุฑุดูุงุณ ุดูุง :ุขูุง ูุนู\nโ๏ธุชุญูู ุจู ุฑูุฒ ุจุง ุณูุฏ ู ูุฏุงุฑฺฉ ุขูุงุฏู\nโ๏ธุฎูุฏุฑู ุฎุดฺฉ ุูุงุจู ุฑูุช ุญุถูุฑ\nโ๏ธุญู ฺฉุงุฑุดูุงุณ ูุจู ุงุฒ ุฎุฑุฏ ุจุง ุดูุง\nโ๏ธ ุชูุงู ุฎูุฏุฑููุง ุฏุงุฑุง ฺฏุงุฑุงูุช ูุนุงู ู ุจูู ูุงูู ูุจุงุดุฏ.\nโ๏ธูุงุจู ูุนุงูุถู ",
    "ฺฉุงุฑฺฉุฑุฏ": "ุตูุฑ ฺฉูููุชุฑ",
    "ููุน ุณูุฎุช": "ุจูุฒู",
    "ฺฏุฑุจฺฉุณ": "ุงุชููุงุชฺฉ",
    "ูุถุนุช ุจุฏูู": "ุจุฏูู ุฑูฺฏ",
    "ุฑูฺฏ ุจุฏูู": "ุณูุฏ",
    "ุฑูฺฏ ุฏุงุฎู": "ุฏุงุฎู ูุดฺฉ",
    "ุญุฌู ููุชูุฑ": "1.5 ูุชุฑ",
    "ูพุดุฑุงูู": "4 ุณููุฏุฑ ุชูุฑุจูุดุงุฑฺ TGDi"
  },
  {
    "ูุงู": "ูููฺฉุณุ ุชฺฏู 8 ูพุฑู ูฺฉุณ",
    "ุณุงู ุณุงุฎุช": "1404",
    "ูุฏู": "IE",
    "ุชุงู": "ุฏูุงู ูพุด",
    "ููุช": "ุชูุงูู",
    "ุขุฏุฑุณ": "ุฑ / ุดูุฑุฑ ",
    "ุชูุถุญุงุช": " ุชูุถุญุงุช ููุงูุฏฺฏ ุงูุชุฎุงุฑ ฺฉุฏ 368 ุจุง ฺฉูุงู ุงุญุชุฑุงู ู ุงูุชุฎุงุฑ ุฏุฑ ุฎุฏูุช ุดูุงุณุช โุดุฑุงุท ุจู ุตูุฑุช ููุฏ ู ุงูุณุงุท ุจุง ฺฉูุชุฑู ุณูุฏ โุงุณุชูุงุฏู ุงุฒ ูพูุดุด ูฺู ุญูุงุช ุชุนูุฑฺฏุงู vip ูพุณ ุงุฒ ุฎุฑุฏ โฺฏุงุฑุงูุช ุฎูุฏุฑู 7 ุณุงูโุชุญูู ุฏุฑ ฺฉูุชุงู ุชุฑู ุฒูุงู โุฌูุช ุญูุธ ุณูุงูุช ูููุทูุงู ุนุฒุฒุุซุจุช ูุงู ุจู ุตูุฑุช ุบุฑ ุญุถูุฑ ูุฒ ุงูุฌุงู ูุดูุฏ",
    "ฺฉุงุฑฺฉุฑุฏ": "ุตูุฑ ฺฉูููุชุฑ",
    "ููุน ุณูุฎุช": "ุจูุฒู",
    "ฺฏุฑุจฺฉุณ": "ุงุชููุงุชฺฉ",
    "ูุถุนุช ุจุฏูู": "ุจุฏูู ุฑูฺฏ",
    "ุฑูฺฏ ุจุฏูู": "ูุดฺฉ",
    "ุฑูฺฏ ุฏุงุฎู": "ุฏุงุฎู ูุดฺฉ",
    "ุญุฌู ููุชูุฑ": "2.0 ูุชุฑ",
    "ูพุดุฑุงูู": "4 ุณููุฏุฑ ุชูุฑุจูุดุงุฑฺ (4J20)",
    "ุดุชุงุจ": "8.1 ุซุงูู",
    "ูุตุฑู ุชุฑฺฉุจ": "7.9 ูุชุฑ ุฏุฑ ุตุฏ ฺฉูููุชุฑ"
  },
  {
    "ูุงู": "ูููฺฉุณุ ุขุฑุฒู 8",
    "ุณุงู ุณุงุฎุช": "1404",
    "ูุฏู": "ุงฺฉุณููุช",
    "ุชุงู": "ุฏูุงู ูพุด",
    "ููุช": "ุชูุงูู",
    "ุขุฏุฑุณ": "ุฑ / ุดูุฑุฑ ",
    "ุชูุถุญุงุช": " ุชูุถุญุงุช ููุงูุฏฺฏ ุงูุชุฎุงุฑ ฺฉุฏ 368 ุจุง ฺฉูุงู ุงุญุชุฑุงู ู ุงูุชุฎุงุฑ ุฏุฑ ุฎุฏูุช ุดูุงุณุช โุดุฑุงุท ุจู ุตูุฑุช ููุฏ ู ุงูุณุงุท ุจุง ฺฉูุชุฑู ุณูุฏ โุงุณุชูุงุฏู ุงุฒ ูพูุดุด ูฺู ุญูุงุช ุชุนูุฑฺฏุงู vip ูพุณ ุงุฒ ุฎุฑุฏ โฺฏุงุฑุงูุช ุฎูุฏุฑู 7 ุณุงู โุชุญูู ุฏุฑ ฺฉูุชุงู ุชุฑู ุฒูุงู โุฌูุช ุญูุธ ุณูุงูุช ูููุทูุงู ุนุฒุฒุุซุจุช ูุงู ุจู ุตูุฑุช ุบุฑ ุญุถูุฑ ูุฒ ุงูุฌุงู ูุดูุฏ",
    "ฺฉุงุฑฺฉุฑุฏ": "ุตูุฑ ฺฉูููุชุฑ",
    "ููุน ุณูุฎุช": "ุจูุฒู",
    "ฺฏุฑุจฺฉุณ": "ุงุชููุงุชฺฉ",
    "ูุถุนุช ุจุฏูู": "ุจุฏูู ุฑูฺฏ",
    "ุฑูฺฏ ุจุฏูู": "ุณูุฏ",
    "ุฑูฺฏ ุฏุงุฎู": "ุฏุงุฎู ูุดฺฉ",
    "ุญุฌู ููุชูุฑ": "2 ูุชุฑ",
    "ูพุดุฑุงูู": "4 ุณููุฏุฑ ุชูุฑุจูุดุงุฑฺ (4J20)",
    "ุดุชุงุจ": "7.6 ุซุงูู",
    "ูุตุฑู ุชุฑฺฉุจ": "6.8 ูุชุฑ ุฏุฑ ุตุฏ ฺฉูููุชุฑ"
  },
  {
    "ูุงู": "ฺฉ ุงู ุณุ J7",
    "ุณุงู ุณุงุฎุช": "1404",
    "ูุฏู": "ุงุชููุงุชฺฉ",
    "ุชุงู": "ุฏูุงู ูพุด",
    "ููุช": "ุชูุงูู",
    "ุขุฏุฑุณ": "ุชูุฑุงู / ุตุฏุฑ",
    "ุชูุถุญุงุช": " ุชูุถุญุงุช ุชูุถุญุงุช\nโญ ููุงูุฏฺฏ ูุฌุงุฒ ฺฉุฑูุงู ููุชูุฑ ฺฉุฏ 314 ุฑูุน ูุงโญ\nโญ ูุฑูุด ููุฏ\nโ๏ธุชุญูู ููุฑ\nโ๏ธุฎุฑุฏ ุนุงู ู ูุทูุฆู",
    "ฺฉุงุฑฺฉุฑุฏ": "ุตูุฑ ฺฉูููุชุฑ",
    "ููุน ุณูุฎุช": "ุจูุฒู",
    "ฺฏุฑุจฺฉุณ": "ุงุชููุงุชฺฉ",
    "ูุถุนุช ุจุฏูู": "ุจุฏูู ุฑูฺฏ",
    "ุฑูฺฏ ุจุฏูู": "ุฎุงฺฉุณุชุฑ",
    "ุฑูฺฏ ุฏุงุฎู": "ุฏุงุฎู ูุดฺฉ",
    "ุญุฌู ููุชูุฑ": "1.5 ูุชุฑ",
    "ูพุดุฑุงูู": "4 ุณููุฏุฑ ุชูุฑุจูุดุงุฑฺ TGDi"
  },
  {
    "ูุงู": "ูููฺฉุณุ FX",
    "ุณุงู ุณุงุฎุช": "1404",
    "ูุฏู": "ูพุฑููู FWD",
    "ุชุงู": "ุฏูุงู ูพุด",
    "ููุช": "ุชูุงูู",
    "ุขุฏุฑุณ": "ุฑ / ุดูุฑุฑ ",
    "ุชูุถุญุงุช": " ุชูุถุญุงุช ููุงูุฏฺฏ ุงูุชุฎุงุฑ ฺฉุฏ 368 ุจุง ฺฉูุงู ุงุญุชุฑุงู ู ุงูุชุฎุงุฑ ุฏุฑ ุฎุฏูุช ุดูุงุณุช โุดุฑุงุท ุจู ุตูุฑุช ููุฏ ู ุงูุณุงุท ุจุง ฺฉูุชุฑู ุณูุฏ โุงุณุชูุงุฏู ุงุฒ ูพูุดุด ูฺู ุญูุงุช ุชุนูุฑฺฏุงู vip ูพุณ ุงุฒ ุฎุฑุฏ โฺฏุงุฑุงูุช ุฎูุฏุฑู 5 ุณุงู ุจุง 2 ุณุงู ุณุฑูุณ ุฑุงฺฏุงูโุชุญูู ุฏุฑ ฺฉูุชุงู ุชุฑู ุฒูุงู โุฌูุช ุญูุธ ุณูุงูุช ูููุทูุงู ุนุฒุฒุุซุจุช ูุงู ุจู ุตูุฑุช ุบุฑ ุญุถูุฑ ูุฒ ุงูุฌุงู ูุดูุฏ",
    "ฺฉุงุฑฺฉุฑุฏ": "ุตูุฑ ฺฉูููุชุฑ",
    "ููุน ุณูุฎุช": "ุจูุฒู",
    "ฺฏุฑุจฺฉุณ": "ุงุชููุงุชฺฉ",
    "ูุถุนุช ุจุฏูู": "ุจุฏูู ุฑูฺฏ",
    "ุฑูฺฏ ุจุฏูู": "ุณูุฏ",
    "ุฑูฺฏ ุฏุงุฎู": "ุฏุงุฎู ูุดฺฉ",
    "ุญุฌู ููุชูุฑ": "1.6 ูุชุฑ",
    "ูพุดุฑุงูู": "4 ุณููุฏุฑ ุชูุฑุจูุดุงุฑฺ (4J16)",
    "ุดุชุงุจ": "8 ุซุงูู",
    "ูุตุฑู ุชุฑฺฉุจ": "6.8 ูุชุฑ ุฏุฑ ุตุฏ ฺฉูููุชุฑ"
  },
  {
    "ูุงู": "ูููฺฉุณุ FX",
    "ุณุงู ุณุงุฎุช": "1403",
    "ูุฏู": "ูพุฑููู FWD",
    "ุชุงู": "ุฏูุงู ูพุด",
    "ููุช": 2590000000.0,
    "ุขุฏุฑุณ": "ุชูุฑุงู / ุดูุฏ ูุทูุฑ",
    "ุชูุถุญุงุช": " ุชูุถุญุงุช ----- ฺู ููุฏ -----\nโ ูุดุงูุฑ ู ฺฉุงุฑุดูุงุณ ุดูุง : ุฎุงูู ุฌุงูุฏ\nโฝ๏ธ ๏ธุชุญูู ุจู ุฑูุฒ ุจุง ุณูุฏ ู ูุฏุงุฑฺฉ ุขูุงุฏู .\nโฝ๏ธ๏ธ ุฎูุฏุฑู ุฎุดฺฉ ุูุงุจู ุฑูุช ุญุถูุฑ .\nโฝ๏ธ๏ธ ุญู ฺฉุงุฑุดูุงุณ ูุจู ุงุฒ ุฎุฑุฏ ุจุง ุดูุง .\nโฝ ๏ธ ุชูุงู ุฎูุฏุฑููุง ุฏุงุฑุง ฺฏุงุฑุงูุช ูุนุงู ู ุจูู ูุงูู ูุจุงุดุฏ .\n๏ธโ ูุงุจู ูุนุงูุถู ",
    "ฺฉุงุฑฺฉุฑุฏ": "ุตูุฑ ฺฉูููุชุฑ",
    "ููุน ุณูุฎุช": "ุจูุฒู",
    "ฺฏุฑุจฺฉุณ": "ุงุชููุงุชฺฉ",
    "ูุถุนุช ุจุฏูู": "ุจุฏูู ุฑูฺฏ",
    "ุฑูฺฏ ุจุฏูู": "ุณูุฏ",
    "ุฑูฺฏ ุฏุงุฎู": "ุฏุงุฎู ูุดฺฉ",
    "ุญุฌู ููุชูุฑ": "1.6 ูุชุฑ",
    "ูพุดุฑุงูู": "4 ุณููุฏุฑ ุชูุฑุจูุดุงุฑฺ (4J16)",
    "ุดุชุงุจ": "8 ุซุงูู",
    "ูุตุฑู ุชุฑฺฉุจ": "6.8 ูุชุฑ ุฏุฑ ุตุฏ ฺฉูููุชุฑ"
  },
  {
    "ูุงู": "ูููฺฉุณุ ุชฺฏู 7 ูพุฑู ูฺฉุณ",
    "ุณุงู ุณุงุฎุช": "1403",
    "ูุฏู": "1.6 ูุชุฑ ุชูุฑุจู 2WD",
    "ุชุงู": "ุฏูุงู ูพุด",
    "ููุช": "ุชูุงูู",
    "ุขุฏุฑุณ": "ุฑ / ุดูุฑุฑ ",
    "ุชูุถุญุงุช": " ุชูุถุญุงุช ููุงูุฏฺฏ ุงูุชุฎุงุฑ ฺฉุฏ 368 ุจุง ฺฉูุงู ุงุญุชุฑุงู ู ุงูุชุฎุงุฑ ุฏุฑ ุฎุฏูุช ุดูุงุณุช โุดุฑุงุท ุจู ุตูุฑุช ููุฏ ู ุงูุณุงุท ุจุง ฺฉูุชุฑู ุณูุฏ โุงุณุชูุงุฏู ุงุฒ ูพูุดุด ูฺู ุญูุงุช ุชุนูุฑฺฏุงู vip ูพุณ ุงุฒ ุฎุฑุฏ โฺฏุงุฑุงูุช ุฎูุฏุฑู 5 ุณุงู ุจุง 2 ุณุงู ุณุฑูุณ ุฑุงฺฏุงูโุชุญูู ุฏุฑ ฺฉูุชุงู ุชุฑู ุฒูุงู โุฌูุช ุญูุธ ุณูุงูุช ูููุทูุงู ุนุฒุฒุุซุจุช ูุงู ุจู ุตูุฑุช ุบุฑ ุญุถูุฑ ูุฒ ุงูุฌุงู ูุดูุฏ",
    "ฺฉุงุฑฺฉุฑุฏ": "ุตูุฑ ฺฉูููุชุฑ",
    "ููุน ุณูุฎุช": "ุจูุฒู",
    "ฺฏุฑุจฺฉุณ": "ุงุชููุงุชฺฉ",
    "ูุถุนุช ุจุฏูู": "ุจุฏูู ุฑูฺฏ",
    "ุฑูฺฏ ุจุฏูู": "ููฺฉ ูุฏุงุฏ",
    "ุฑูฺฏ ุฏุงุฎู": "ุฏุงุฎู ูุดฺฉ",
    "ุญุฌู ููุชูุฑ": "1.6 ูุชุฑ",
    "ูพุดุฑุงูู": "4 ุณููุฏุฑ ุชูุฑุจูุดุงุฑฺ (4J16)",
    "ูุตุฑู ุชุฑฺฉุจ": "8.5 ูุชุฑ ุฏุฑ ุตุฏ ฺฉูููุชุฑ"
  },
  {
    "ูุงู": "ูููฺฉุณุ ุชฺฏู 7 ูพุฑู ูุจุฑุฏ",
    "ุณุงู ุณุงุฎุช": "1404",
    "ูุฏู": "e ูพูุงุณ",
    "ุชุงู": "ุฏูุงู ูพุด",
    "ููุช": "ุชูุงูู",
    "ุขุฏุฑุณ": "ุฑ / ุดูุฑุฑ ",
    "ุชูุถุญุงุช": " ุชูุถุญุงุช ููุงูุฏฺฏ ุงูุชุฎุงุฑ ฺฉุฏ 368 ุจุง ฺฉูุงู ุงุญุชุฑุงู ู ุงูุชุฎุงุฑ ุฏุฑ ุฎุฏูุช ุดูุงุณุช โุดุฑุงุท ุจู ุตูุฑุช ููุฏ ู ุงูุณุงุท ุจุง ฺฉูุชุฑู ุณูุฏ โุงุณุชูุงุฏู ุงุฒ ูพูุดุด ูฺู ุญูุงุช ุชุนูุฑฺฏุงู vip ูพุณ ุงุฒ ุฎุฑุฏ โฺฏุงุฑุงูุช ุฎูุฏุฑู 7 ุณุงู โุชุญูู ุฏุฑ ฺฉูุชุงู ุชุฑู ุฒูุงู โุฌูุช ุญูุธ ุณูุงูุช ูููุทูุงู ุนุฒุฒุุซุจุช ูุงู ุจู ุตูุฑุช ุบุฑ ุญุถูุฑ ูุฒ ุงูุฌุงู ูุดูุฏ.",
    "ฺฉุงุฑฺฉุฑุฏ": "ุตูุฑ ฺฉูููุชุฑ",
    "ููุน ุณูุฎุช": "ูุจุฑุฏ",
    "ฺฏุฑุจฺฉุณ": "ุงุชููุงุชฺฉ",
    "ูุถุนุช ุจุฏูู": "ุจุฏูู ุฑูฺฏ",
    "ุฑูฺฏ ุจุฏูู": "ุณูุฏ",
    "ุฑูฺฏ ุฏุงุฎู": "ุฏุงุฎู ูุดฺฉ",
    "ุญุฌู ููุชูุฑ": "1.5 ูุชุฑ",
    "ูพุดุฑุงูู": "4 ุณููุฏุฑ ุชูุฑุจูุดุงุฑฺ (4T15C) ุจุง 2 ููุชูุฑ ุงูฺฉุชุฑฺฉ",
    "ุดุชุงุจ": "7.5 ุซุงูู",
    "ูุตุฑู ุชุฑฺฉุจ": "5.9 ูุชุฑ ุฏุฑ ุตุฏ ฺฉูููุชุฑ"
  },
  {
    "ูุงู": "ูููฺฉุณุ ุชฺฏู 7 ูพุฑู",
    "ุณุงู ุณุงุฎุช": "1404",
    "ูุฏู": "ูพุฑููู",
    "ุชุงู": "ุฏูุงู ูพุด",
    "ููุช": "ุชูุงูู",
    "ุขุฏุฑุณ": "ุฑ / ุดูุฑุฑ ",
    "ุชูุถุญุงุช": " ุชูุถุญุงุช ููุงูุฏฺฏ ุงูุชุฎุงุฑ ฺฉุฏ 368 ุจุง ฺฉูุงู ุงุญุชุฑุงู ู ุงูุชุฎุงุฑ ุฏุฑ ุฎุฏูุช ุดูุงุณุช โุดุฑุงุท ุจู ุตูุฑุช ููุฏ ู ุงูุณุงุท ุจุง ฺฉูุชุฑู ุณูุฏ โุงุณุชูุงุฏู ุงุฒ ูพูุดุด ูฺู ุญูุงุช ุชุนูุฑฺฏุงู vip ูพุณ ุงุฒ ุฎุฑุฏ โฺฏุงุฑุงูุช ุฎูุฏุฑู 5 ุณุงู ุจุง 2 ุณุงู ุณุฑูุณ ุฑุงฺฏุงูโุชุญูู ุฏุฑ ฺฉูุชุงู ุชุฑู ุฒูุงู โุฌูุช ุญูุธ ุณูุงูุช ูููุทูุงู ุนุฒุฒุุซุจุช ูุงู ุจู ุตูุฑุช ุบุฑ ุญุถูุฑ ูุฒ ุงูุฌุงู ูุดูุฏ",
    "ฺฉุงุฑฺฉุฑุฏ": "ุตูุฑ ฺฉูููุชุฑ",
    "ููุน ุณูุฎุช": "ุจูุฒู",
    "ฺฏุฑุจฺฉุณ": "ุงุชููุงุชฺฉ",
    "ูุถุนุช ุจุฏูู": "ุจุฏูู ุฑูฺฏ",
    "ุฑูฺฏ ุจุฏูู": "ูุดฺฉ",
    "ุฑูฺฏ ุฏุงุฎู": "ุฏุงุฎู ูุดฺฉ",
    "ุญุฌู ููุชูุฑ": "1.5 ูุชุฑ",
    "ูพุดุฑุงูู": "4 ุณููุฏุฑ ุชูุฑุจู ุดุงุฑฺ",
    "ูุตุฑู ุชุฑฺฉุจ": "8.4 ูุชุฑ ุฏุฑ ุตุฏ ฺฉูููุชุฑ"
  },
  {
    "ูุงู": "ูููฺฉุณุ ุขุฑุฒู 6 ุฌ ุช",
    "ุณุงู ุณุงุฎุช": "1404",
    "ูุฏู": "ุงฺฉุณููุช",
    "ุชุงู": "ุฏูุงู ูพุด",
    "ููุช": "ุชูุงูู",
    "ุขุฏุฑุณ": "ุฑ / ุดูุฑุฑ ",
    "ุชูุถุญุงุช": " ุชูุถุญุงุช ููุงูุฏฺฏ ุงูุชุฎุงุฑ ฺฉุฏ 368 ุจุง ฺฉูุงู ุงุญุชุฑุงู ู ุงูุชุฎุงุฑ ุฏุฑ ุฎุฏูุช ุดูุงุณุช โุดุฑุงุท ุจู ุตูุฑุช ููุฏ ู ุงูุณุงุท ุจุง ฺฉูุชุฑู ุณูุฏ โุงุณุชูุงุฏู ุงุฒ ูพูุดุด ูฺู ุญูุงุช ุชุนูุฑฺฏุงู vip ูพุณ ุงุฒ ุฎุฑุฏ โฺฏุงุฑุงูุช ุฎูุฏุฑู 5 ุณุงู ุจุง 2 ุณุงู ุณุฑูุณ ุฑุงฺฏุงูโุชุญูู ุฏุฑ ฺฉูุชุงู ุชุฑู ุฒูุงู โุฌูุช ุญูุธ ุณูุงูุช ูููุทูุงู ุนุฒุฒุุซุจุช ูุงู ุจู ุตูุฑุช ุบุฑ ุญุถูุฑ ูุฒ ุงูุฌุงู ูุดูุฏ",
    "ฺฉุงุฑฺฉุฑุฏ": "ุตูุฑ ฺฉูููุชุฑ",
    "ููุน ุณูุฎุช": "ุจูุฒู",
    "ฺฏุฑุจฺฉุณ": "ุงุชููุงุชฺฉ",
    "ูุถุนุช ุจุฏูู": "ุจุฏูู ุฑูฺฏ",
    "ุฑูฺฏ ุจุฏูู": "ูุดฺฉ",
    "ุฑูฺฏ ุฏุงุฎู": "ุฏุงุฎู ูุดฺฉ",
    "ุญุฌู ููุชูุฑ": "1.6 ูุชุฑ",
    "ูพุดุฑุงูู": "4 ุณููุฏุฑ ุชูุฑุจูุดุงุฑฺ (4J16)",
    "ุดุชุงุจ": "7.6 ุซุงูู",
    "ูุตุฑู ุชุฑฺฉุจ": "6.6 ูุชุฑ ุฏุฑ ุตุฏ ฺฉูููุชุฑ"
  },
  {
    "ูุงู": "ูููฺฉุณุ ุขุฑุฒู 6 ูพุฑู",
    "ุณุงู ุณุงุฎุช": "1404",
    "ูุฏู": "ุงุชููุงุชฺฉ",
    "ุชุงู": "ุฏูุงู ูพุด",
    "ููุช": "ุชูุงูู",
    "ุขุฏุฑุณ": "ุฑ / ุดูุฑุฑ ",
    "ุชูุถุญุงุช": " ุชูุถุญุงุช ููุงูุฏฺฏ ุงูุชุฎุงุฑ ฺฉุฏ 368 ุจุง ฺฉูุงู ุงุญุชุฑุงู ู ุงูุชุฎุงุฑ ุฏุฑ ุฎุฏูุช ุดูุงุณุช โุดุฑุงุท ุจู ุตูุฑุช ููุฏ ู ุงูุณุงุท ุจุง ฺฉูุชุฑู ุณูุฏ โุงุณุชูุงุฏู ุงุฒ ูพูุดุด ูฺู ุญูุงุช ุชุนูุฑฺฏุงู vip ูพุณ ุงุฒ ุฎุฑุฏ โฺฏุงุฑุงูุช ุฎูุฏุฑู 5 ุณุงู ุจุง 2 ุณุงู ุณุฑูุณ ุฑุงฺฏุงูโุชุญูู ุฏุฑ ฺฉูุชุงู ุชุฑู ุฒูุงู โุฌูุช ุญูุธ ุณูุงูุช ูููุทูุงู ุนุฒุฒุุซุจุช ูุงู ุจู ุตูุฑุช ุบุฑ ุญุถูุฑ ูุฒ ุงูุฌุงู ูุดูุฏ",
    "ฺฉุงุฑฺฉุฑุฏ": "ุตูุฑ ฺฉูููุชุฑ",
    "ููุน ุณูุฎุช": "ุจูุฒู",
    "ฺฏุฑุจฺฉุณ": "ุงุชููุงุชฺฉ",
    "ูุถุนุช ุจุฏูู": "ุจุฏูู ุฑูฺฏ",
    "ุฑูฺฏ ุจุฏูู": "ูุดฺฉ",
    "ุฑูฺฏ ุฏุงุฎู": "ุฏุงุฎู ูุดฺฉ",
    "ุญุฌู ููุชูุฑ": "1.5 ูุชุฑ",
    "ูพุดุฑุงูู": "4 ุณููุฏุฑ ุชูุฑุจูุดุงุฑฺ (4T15C)",
    "ุดุชุงุจ": "10.5 ุซุงูู",
    "ูุตุฑู ุชุฑฺฉุจ": "6.9 ูุชุฑ ุฏุฑ ุตุฏ ฺฉูููุชุฑ"
  },
  {
    "ูุงู": "ุงู ู ุงูุ X55 PRO",
    "ุณุงู ุณุงุฎุช": "1404",
    "ูุฏู": "IE",
    "ุชุงู": "ุฏูุงู ูพุด",
    "ููุช": "ุชูุงูู",
    "ุขุฏุฑุณ": "ุฑ / ุดูุฑุฑ ",
    "ุชูุถุญุงุช": " ุชูุถุญุงุช ููุงูุฏฺฏ ุงูุชุฎุงุฑ ฺฉุฏ 368 ุจุง ฺฉูุงู ุงุญุชุฑุงู ู ุงูุชุฎุงุฑ ุฏุฑ ุฎุฏูุช ุดูุงุณุช โุดุฑุงุท ุจู ุตูุฑุช ููุฏ ู ุงูุณุงุท ุจุง ฺฉูุชุฑู ุณูุฏ โุงุณุชูุงุฏู ุงุฒ ูพูุดุด ูฺู ุญูุงุช ุชุนูุฑฺฏุงู vip ูพุณ ุงุฒ ุฎุฑุฏ โฺฏุงุฑุงูุช ุฎูุฏุฑู 5 ุณุงู ุจุง 2 ุณุงู ุณุฑูุณ ุฑุงฺฏุงูโุชุญูู ุฏุฑ ฺฉูุชุงู ุชุฑู ุฒูุงู โุฌูุช ุญูุธ ุณูุงูุช ูููุทูุงู ุนุฒุฒุุซุจุช ูุงู ุจู ุตูุฑุช ุบุฑ ุญุถูุฑ ูุฒ ุงูุฌุงู ูุดูุฏ",
    "ฺฉุงุฑฺฉุฑุฏ": "ุตูุฑ ฺฉูููุชุฑ",
    "ููุน ุณูุฎุช": "ุจูุฒู",
    "ฺฏุฑุจฺฉุณ": "ุงุชููุงุชฺฉ",
    "ูุถุนุช ุจุฏูู": "ุจุฏูู ุฑูฺฏ",
    "ุฑูฺฏ ุจุฏูู": "ูุดฺฉ",
    "ุฑูฺฏ ุฏุงุฎู": "ุฏุงุฎู ูุดฺฉ",
    "ุญุฌู ููุชูุฑ": "1.5 ูุชุฑ",
    "ูพุดุฑุงูู": "4 ุณููุฏุฑ ุชูุฑุจูุดุงุฑฺ ุจููู ุดุฏู"
  },
  {
    "ูุงู": "ฺฉ ุงู ุณุ J7",
    "ุณุงู ุณุงุฎุช": "1404",
    "ูุฏู": "ุงุชููุงุชฺฉ",
    "ุชุงู": "ุฏูุงู ูพุด",
    "ููุช": "ุชูุงูู",
    "ุขุฏุฑุณ": "ุชูุฑุงู / ุงูุฏุฑุฒฺฏู",
    "ุชูุถุญุงุช": " ุชูุถุญุงุช โุงูุฏ ฺฏุงูุฑ\nุจุด ุงุฒ ฑต ุณุงู ุณุงุจูู ุฏุฑ ุฎุฑุฏ ู ูุฑูุด ูุงุดู\nุนุถู ุฑุณู ุงุชุญุงุฏู\nุชุญูู ููุฑ ุจุง ุงูฺฉุงู ฺฉุงุฑุดูุงุณ\nโููุช ุขุฎุฑ ุฑุง ุงุฒ ูุง ุจุฎูุงูุฏ",
    "ฺฉุงุฑฺฉุฑุฏ": "ุตูุฑ ฺฉูููุชุฑ",
    "ููุน ุณูุฎุช": "ุจูุฒู",
    "ฺฏุฑุจฺฉุณ": "ุงุชููุงุชฺฉ",
    "ูุถุนุช ุจุฏูู": "ุจุฏูู ุฑูฺฏ",
    "ุฑูฺฏ ุจุฏูู": "ุณูุฏ",
    "ุฑูฺฏ ุฏุงุฎู": "ุฏุงุฎู ูุดฺฉ",
    "ุญุฌู ููุชูุฑ": "1.5 ูุชุฑ",
    "ูพุดุฑุงูู": "4 ุณููุฏุฑ ุชูุฑุจูุดุงุฑฺ TGDi"
  },
  {
    "ูุงู": "ฺฉ ุงู ุณุ T9",
    "ุณุงู ุณุงุฎุช": "1404",
    "ูุฏู": "2 ูุชุฑ ุชูุฑุจู",
    "ุชุงู": "ุฏูุงู ูพุด",
    "ููุช": 2750000000.0,
    "ุขุฏุฑุณ": "ุชูุฑุงู / ุตุฏุฑ",
    "ุชูุถุญุงุช": " ุชูุถุญุงุช ๐ฉููุงูุฏฺฏ ูุฌุงุฒ ฺฉุฑูุงู ููุชูุฑ ฺฉุฏ 314 ุฑูุน ๐ฉ\nโุชุญูู : ููุท 20 ุฑูุฒ ฺฉุงุฑ \nโุณูุฏ: ุชฺฉ ุจุฑฺฏ ุ ูุณุชูู ุจู ูุงู ุฎุฑุฏุงุฑ \nโุญูุงูู ุดุฑฺฉุช ูุนุชุจุฑ \n๐ูุฒุงุง :\nโุตุฑูู ุฌู ุฏุฑ ุฒูุงู ู ูุฒูู \nโุฌูุช ฺฉุณุจ ุงุทูุงุนุงุช ุจุดุชุฑ ุจุงููฺฉุงุฑุงู ูุง ุฏุฑ ุงุฑุชุจุงุท ุจุงุดุฏ",
    "ฺฉุงุฑฺฉุฑุฏ": "ุตูุฑ ฺฉูููุชุฑ",
    "ููุน ุณูุฎุช": "ุจูุฒู",
    "ฺฏุฑุจฺฉุณ": "ุงุชููุงุชฺฉ",
    "ูุถุนุช ุจุฏูู": "ุจุฏูู ุฑูฺฏ",
    "ุฑูฺฏ ุจุฏูู": "ูุดฺฉ",
    "ุฑูฺฏ ุฏุงุฎู": "ุฏุงุฎู ูุดฺฉ",
    "ุญุฌู ููุชูุฑ": "2.0 ูุชุฑ",
    "ูพุดุฑุงูู": "4 ุณููุฏุฑ ุชูุฑุจูุดุงุฑฺ (HFC4DB2)"
  },
  {
    "ูุงู": "ูุงูุงุ S5",
    "ุณุงู ุณุงุฎุช": "1403",
    "ูุฏู": "6 ุณุฑุนุชู ุงุชููุงุชฺฉ",
    "ุชุงู": "ุฏูุงู ูพุด",
    "ููุช": 1840000000.0,
    "ุขุฏุฑุณ": "ุชูุฑุงู / ุดูุฏ ูุทูุฑ",
    "ุชูุถุญุงุช": " ุชูุถุญุงุช ----- ฺู ููุฏ -----\nูุดุงูุฑ ู ฺฉุงุฑุดูุงุณ ุดูุง : ุฎุงูู ุดุฑู\nโ๏ธุชุญูู ุจู ุฑูุฒ ุจุง ุณูุฏ ู ูุฏุงุฑฺฉ ุขูุงุฏู\nโ๏ธุฎูุฏุฑู ุฎุดฺฉ ุูุงุจู ุฑูุช ุญุถูุฑ\nโ๏ธุญู ฺฉุงุฑุดูุงุณ ูุจู ุงุฒ ุฎุฑุฏ ุจุง ุดูุง\nโ๏ธ ุชูุงู ุฎูุฏุฑููุง ุฏุงุฑุง ฺฏุงุฑุงูุช ูุนุงู ู ุจูู ูุงูู ูุจุงุดุฏ.\nโ๏ธูุงุจู ูุนุงูุถู ",
    "ฺฉุงุฑฺฉุฑุฏ": "ุตูุฑ ฺฉูููุชุฑ",
    "ููุน ุณูุฎุช": "ุจูุฒู",
    "ฺฏุฑุจฺฉุณ": "ุงุชููุงุชฺฉ",
    "ูุถุนุช ุจุฏูู": "ุจุฏูู ุฑูฺฏ",
    "ุฑูฺฏ ุจุฏูู": "ุณูุฏ",
    "ุฑูฺฏ ุฏุงุฎู": "ุฏุงุฎู ูุดฺฉ",
    "ุญุฌู ููุชูุฑ": "1.5 ูุชุฑ",
    "ูพุดุฑุงูู": "4 ุณููุฏุฑ ุชูุฑุจูุดุงุฑฺ",
    "ุดุชุงุจ": "9 ุซุงูู",
    "ูุตุฑู ุชุฑฺฉุจ": "8 ูุชุฑ ุฏุฑ ุตุฏ ฺฉูููุชุฑ"
  },
  {
    "ูุงู": "ูพุด ูุฑูุด ฺฉ ุงู ุณุ ุงฺฏู",
    "ุณุงู ุณุงุฎุช": "1404",
    "ูุฏู": "1.5 ูุชุฑ",
    "ุชุงู": "ุฏูุงู ูพุด",
    "ููุช": 1050000000.0,
    "ุขุฏุฑุณ": "ุชูุฑุงู / ุฑุณุงูุช",
    "ุชูุถุญุงุช": " ุชูุถุญุงุช โญ ููุงูุฏฺฏ ุฑุณู ฺฉุฑูุงู ููุชูุฑ ูุฑุงุฏ ฺฉุฏ 1751 โญ\nโ ุชุญูู 20 ุฑูุฒ ฺฉุงุฑ \nโุญูุงูู ูุนุชุจุฑ ุดุฑฺฉุช ุณูุฏ ุงุฒ ฺฉููพุงู ุจูุงู ุฎุฑุฏุงุฑ\nโ ูุฑุตุช ุงุณุชุซูุงุฆ ุจุง ุชุนุฏุงุฏ ูุญุฏูุฏ\n@@ุฌูุช ฺฉุณุจ ุงุทูุงุนุงุช ุจุดุชุฑ ุจุง ูุง ุฏุฑ ุงุฑุชุจุงุท ุจุงุดุฏ.",
    "ฺฉุงุฑฺฉุฑุฏ": "ุตูุฑ ฺฉูููุชุฑ",
    "ููุน ุณูุฎุช": "ุจูุฒู",
    "ฺฏุฑุจฺฉุณ": "ุงุชููุงุชฺฉ",
    "ูุถุนุช ุจุฏูู": "ุจุฏูู ุฑูฺฏ",
    "ุฑูฺฏ ุจุฏูู": "ุณูุฏ",
    "ุฑูฺฏ ุฏุงุฎู": "ุฏุงุฎู ูุดฺฉ",
    "ุญุฌู ููุชูุฑ": "1.5 ูุชุฑ",
    "ูพุดุฑุงูู": "4 ุณููุฏุฑ",
    "ุดุชุงุจ": "12.5 ุซุงูู",
    "ูุตุฑู ุชุฑฺฉุจ": "6.8 ูุชุฑ ุฏุฑ ุตุฏ ฺฉูููุชุฑ"
  },
  {
    "ูุงู": "ูุฏูุชุ ูพุฑุณุชฺ",
    "ุณุงู ุณุงุฎุช": "1403",
    "ูุฏู": "ุชูพ 1 ูพูุฌ ููุฑู",
    "ุชุงู": "ุฏูุงู ูพุด",
    "ููุช": 3400000000.0,
    "ุขุฏุฑุณ": "ุชูุฑุงู / ุดูุฏ ูุทูุฑ",
    "ุชูุถุญุงุช": " ุชูุถุญุงุช ----- ฺู ููุฏ -----\nูุดุงูุฑ ู ฺฉุงุฑุดูุงุณ ุดูุง :ุขูุง ูุนู\nโ๏ธุชุญูู ุจู ุฑูุฒ ุจุง ุณูุฏ ู ูุฏุงุฑฺฉ ุขูุงุฏู\nโ๏ธุฎูุฏุฑู ุฎุดฺฉ ุูุงุจู ุฑูุช ุญุถูุฑ\nโ๏ธุญู ฺฉุงุฑุดูุงุณ ูุจู ุงุฒ ุฎุฑุฏ ุจุง ุดูุง\nโ๏ธ ุชูุงู ุฎูุฏุฑููุง ุฏุงุฑุง ฺฏุงุฑุงูุช ูุนุงู ู ุจูู ูุงูู ูุจุงุดุฏ.\nโ๏ธูุงุจู ูุนุงูุถู",
    "ฺฉุงุฑฺฉุฑุฏ": "ุตูุฑ ฺฉูููุชุฑ",
    "ููุน ุณูุฎุช": "ุจูุฒู",
    "ฺฏุฑุจฺฉุณ": "ุงุชููุงุชฺฉ",
    "ูุถุนุช ุจุฏูู": "ุจุฏูู ุฑูฺฏ",
    "ุฑูฺฏ ุจุฏูู": "ุณูุฏ",
    "ุฑูฺฏ ุฏุงุฎู": "ุฏุงุฎู ููฺฉุง",
    "ุญุฌู ููุชูุฑ": "1.6 ูุชุฑ",
    "ูพุดุฑุงูู": "4 ุณููุฏุฑ ุชูุฑุจูุดุงุฑฺ (4J16)",
    "ุดุชุงุจ": "9.9 ุซุงูู",
    "ูุตุฑู ุชุฑฺฉุจ": "8.2 ูุชุฑ ุฏุฑ ุตุฏ ฺฉูููุชุฑ"
  },
  {
    "ูุงู": "ูููฺฉุณุ ID.4 Crozz",
    "ุณุงู ุณุงุฎุช": "2024",
    "ูุฏู": "PURE PLUS",
    "ุชุงู": "ุฏูุงู ูพุด",
    "ููุช": 7300000000.0,
    "ุขุฏุฑุณ": "ุชูุฑุงู / ุขุฌูุฏุงูู",
    "ุชูุถุญุงุช": " ุชูุถุญุงุช โ๏ธููุงูุฏฺฏ ุฑุณู ูุงููุช ุฎูุฏุฑู\nโ๏ธููุฏ ู ุงูุณุงุท\nโ๏ธุฎุฏูุงุช vip\nโ๏ธูู ุชุฑู ูุฏู ุจุฑู ูููฺฉุณ ูุงฺฏู\nโ๏ธุทุฑุญ ุชุนูุถ ุฎูุฏุฑู ูุง ฺฉุงุฑฺฉุฑุฏู\nโ๏ธฺฉุงุฑุดูุงุณ ูุฑูุด\nโ๏ธูุตุทู ูุดูุฏ",
    "ฺฉุงุฑฺฉุฑุฏ": "ุตูุฑ ฺฉูููุชุฑ",
    "ููุน ุณูุฎุช": "ุจุฑู",
    "ฺฏุฑุจฺฉุณ": "ุงุชููุงุชฺฉ",
    "ูุถุนุช ุจุฏูู": "ุจุฏูู ุฑูฺฏ",
    "ุฑูฺฏ ุจุฏูู": "ูุดฺฉ",
    "ุฑูฺฏ ุฏุงุฎู": "ุฏุงุฎู ูุดฺฉ"
  },
  {
    "ูุงู": "ุงฺฉุณุชุฑูุ VX",
    "ุณุงู ุณุงุฎุช": "1404",
    "ูุฏู": "2.0 ูุชุฑ ุชูุฑุจู",
    "ุชุงู": "ุฏูุงู ูพุด",
    "ููุช": "ุชูุงูู",
    "ุขุฏุฑุณ": "ุชูุฑุงู / ุงูุฏุฑุฒฺฏู",
    "ุชูุถุญุงุช": " ุชูุถุญุงุช โุงูุฏ ฺฏุงูุฑ\nุจุด ุงุฒ ฑต ุณุงู ุณุงุจูู ุฏุฑ ุฎุฑุฏ ู ูุฑูุด ูุงุดู\nุนุถู ุฑุณู ุงุชุญุงุฏู\nุชุญูู ููุฑ ุจุง ุงูฺฉุงู ฺฉุงุฑุดูุงุณ\nโููุช ุขุฎุฑ ุฑุง ุงุฒ ูุง ุจุฎูุงูุฏ",
    "ฺฉุงุฑฺฉุฑุฏ": "ุตูุฑ ฺฉูููุชุฑ",
    "ููุน ุณูุฎุช": "ุจูุฒู",
    "ฺฏุฑุจฺฉุณ": "ุงุชููุงุชฺฉ",
    "ูุถุนุช ุจุฏูู": "ุจุฏูู ุฑูฺฏ",
    "ุฑูฺฏ ุจุฏูู": "ุฎุงฺฉุณุชุฑ",
    "ุฑูฺฏ ุฏุงุฎู": "ุฏุงุฎู ูุดฺฉ",
    "ุญุฌู ููุชูุฑ": "2.0 ูุชุฑ",
    "ูพุดุฑุงูู": "4 ุณููุฏุฑ ุชูุฑุจูุดุงุฑฺ (4J20)",
    "ุดุชุงุจ": "9 ุซุงูู"
  },
  {
    "ูุงู": "ุณูุฒูฺฉุ ูุฑุงูฺฉุณ ูุจุฑุฏ",
    "ุณุงู ุณุงุฎุช": "2025",
    "ูุฏู": "1.5 ูุชุฑ",
    "ุชุงู": "ุฏูุงู ูพุด",
    "ููุช": 2750000000.0,
    "ุขุฏุฑุณ": "ุชูุฑุงู / ูุทุฑู",
    "ุชูุถุญุงุช": " ุชูุถุญุงุช ูุงุดู ุชุงุฒู ุชุญูู ฺฏุฑูุชู ุดุฏู\nููุฌูุฏ ุฏุฑ ููุงุดฺฏุงู \nุงูฺฉุงู ุจุงุฒุฏุฏ ู ฺฉุงุฑุดูุงุณ ูุจู ุงุฒ ูุฑฺฏููู ูุงุฑุฒ\nุฌูุช ุฎุฑุฏ ููุท ุชูุงุณ ุจฺฏุฑู",
    "ฺฉุงุฑฺฉุฑุฏ": "ุตูุฑ ฺฉูููุชุฑ",
    "ููุน ุณูุฎุช": "ูุจุฑุฏ",
    "ฺฏุฑุจฺฉุณ": "ุงุชููุงุชฺฉ",
    "ูุถุนุช ุจุฏูู": "ุจุฏูู ุฑูฺฏ",
    "ุฑูฺฏ ุจุฏูู": "ููุฑู ุง",
    "ุฑูฺฏ ุฏุงุฎู": "ุฏุงุฎู ูุดฺฉ",
    "ุญุฌู ููุชูุฑ": "1.5 ูุชุฑ",
    "ูพุดุฑุงูู": "4 ุณููุฏุฑ ูุจุฑุฏ ููุงู (K15C)",
    "ุดุชุงุจ": "11 ุซุงูู",
    "ูุตุฑู ุชุฑฺฉุจ": "5.4 ูุชุฑ ุฏุฑ ุตุฏ ฺฉูููุชุฑ"
  },
  {
    "ูุงู": "ูููฺฉุณุ ุชฺฏู 7 ูพุฑู",
    "ุณุงู ุณุงุฎุช": "1403",
    "ูุฏู": "ูพุฑููู",
    "ุชุงู": "ุฏูุงู ูพุด",
    "ููุช": "ุชูุงูู",
    "ุขุฏุฑุณ": "ุชูุฑุงู / ุขุฌูุฏุงูู",
    "ุชูุถุญุงุช": " ุชูุถุญุงุช โ๏ธููุงูุฏฺฏ ุฎุณุฑูุงู\nโ๏ธููุฏ ู ุงูุณุงุท\nโ๏ธููุฑุงู ุจุง ฺฉุงุฑุดูุงุณ\nโ๏ธุฎุฑุฏ ุงูู ู ูุทูุฆู\nโ๏ธุจุฏูู ฺฉูฺฺฉ ุชุฑู ูุฒูู ุงุถุงู\nโ๏ธุทุฑุญ ุชุนูุถ ุฎูุฏุฑู ูุง ฺฉุงุฑฺฉุฑุฏู\nโ๏ธฺฉุงุฑุดูุงุณ ูุฑูุด\nโ๏ธูุตุทู ูุดูุฏ",
    "ฺฉุงุฑฺฉุฑุฏ": "ุตูุฑ ฺฉูููุชุฑ",
    "ููุน ุณูุฎุช": "ุจูุฒู",
    "ฺฏุฑุจฺฉุณ": "ุงุชููุงุชฺฉ",
    "ูุถุนุช ุจุฏูู": "ุจุฏูู ุฑูฺฏ",
    "ุฑูฺฏ ุจุฏูู": "ูุดฺฉ",
    "ุฑูฺฏ ุฏุงุฎู": "ุฏุงุฎู ูุดฺฉ",
    "ุญุฌู ููุชูุฑ": "1.5 ูุชุฑ",
    "ูพุดุฑุงูู": "4 ุณููุฏุฑ ุชูุฑุจู ุดุงุฑฺ",
    "ูุตุฑู ุชุฑฺฉุจ": "8.4 ูุชุฑ ุฏุฑ ุตุฏ ฺฉูููุชุฑ"
  },
  {
    "ูุงู": "ุฌฺฉุ ุฌ 4",
    "ุณุงู ุณุงุฎุช": "1404",
    "ูุฏู": "ุงุชููุงุชฺฉ",
    "ุชุงู": "ุฏูุงู ูพุด",
    "ููุช": 1050000000.0,
    "ุขุฏุฑุณ": "ุชูุฑุงู / ูพููฺฉ",
    "ุชูุถุญุงุช": " ุชูุถุญุงุช ๐ฉููุงูุฏฺฏ ูุฌุงุฒ ฺฉุฑูุงู ููุชูุฑ ฺฉุฏ 1752 ุฑูุน ๐ฉ\nโุชุญูู ููุฑ ู ููุฏ\nโููุฌูุฏ ุฏุฑ ููุงูุฏฺฏ * \nโุฌูุช ฺฉุณุจ ุงุทูุงุนุงุช ุจุดุชุฑ ุจุง ูุง ุฏุฑ ุชูุงุณ ุจุงุดุฏ.",
    "ฺฉุงุฑฺฉุฑุฏ": "ุตูุฑ ฺฉูููุชุฑ",
    "ููุน ุณูุฎุช": "ุจูุฒู",
    "ฺฏุฑุจฺฉุณ": "ุงุชููุงุชฺฉ",
    "ูุถุนุช ุจุฏูู": "ุจุฏูู ุฑูฺฏ",
    "ุฑูฺฏ ุจุฏูู": "ูุดฺฉ",
    "ุฑูฺฏ ุฏุงุฎู": "ุฏุงุฎู ูุดฺฉ",
    "ุญุฌู ููุชูุฑ": "1.5 ูุชุฑ",
    "ูพุดุฑุงูู": "4 ุณููุฏุฑ",
    "ุดุชุงุจ": "11 ุซุงูู",
    "ูุตุฑู ุชุฑฺฉุจ": "6.2 ูุชุฑ ุฏุฑ ุตุฏ ฺฉูููุชุฑ"
  },
  {
    "ูุงู": "ุงู ู ุงูุ X55 PRO",
    "ุณุงู ุณุงุฎุช": "1403",
    "ูุฏู": "IE",
    "ุชุงู": "ุฏูุงู ูพุด",
    "ููุช": 1870000000.0,
    "ุขุฏุฑุณ": "ุชูุฑุงู / ุดูุฏ ูุทูุฑ",
    "ุชูุถุญุงุช": " ุชูุถุญุงุช ----- ฺู ููุฏ -----\nโ ูุดุงูุฑ ู ฺฉุงุฑุดูุงุณ ุดูุง : ุฎุงูู ุฌุงูุฏ\nโฝ๏ธ ๏ธุชุญูู ุจู ุฑูุฒ ุจุง ุณูุฏ ู ูุฏุงุฑฺฉ ุขูุงุฏู .\nโฝ๏ธ๏ธ ุฎูุฏุฑูุฎุดฺฉ ุูุงุจู ุฑูุช ุญุถูุฑ .\nโฝ๏ธ๏ธ ุญู ฺฉุงุฑุดูุงุณ ูุจู ุงุฒ ุฎุฑุฏ ุจุง ุดูุง .\nโฝ ๏ธ ุชูุงู ุฎูุฏุฑููุง ุฏุงุฑุง ฺฏุงุฑุงูุช ูุนุงู ู ุจูู ูุงูู ูุจุงุดุฏ .\n๏ธโ ูุงุจู ูุนุงูุถู",
    "ฺฉุงุฑฺฉุฑุฏ": "ุตูุฑ ฺฉูููุชุฑ",
    "ููุน ุณูุฎุช": "ุจูุฒู",
    "ฺฏุฑุจฺฉุณ": "ุงุชููุงุชฺฉ",
    "ูุถุนุช ุจุฏูู": "ุจุฏูู ุฑูฺฏ",
    "ุฑูฺฏ ุจุฏูู": "ุฎุงฺฉุณุชุฑ",
    "ุฑูฺฏ ุฏุงุฎู": "ุฏุงุฎู ูุดฺฉ",
    "ุญุฌู ููุชูุฑ": "1.5 ูุชุฑ",
    "ูพุดุฑุงูู": "4 ุณููุฏุฑ ุชูุฑุจูุดุงุฑฺ ุจููู ุดุฏู"
  },
  {
    "ูุงู": "ฺฉ ุงู ุณุ ุงฺฏู",
    "ุณุงู ุณุงุฎุช": "1404",
    "ูุฏู": "1.5 ูุชุฑ",
    "ุชุงู": "ุฏูุงู ูพุด",
    "ููุช": 1050000000.0,
    "ุขุฏุฑุณ": "ุชูุฑุงู / ุขุฌูุฏุงูู",
    "ุชูุถุญุงุช": " ุชูุถุญุงุช โ๏ธููุงูุฏฺฏ ุจุฑุชุฑ ฺฉุฑูุงู ููุชูุฑ ุฏุฑ ฺฉุดูุฑ\n(ุฎุณุฑูุงู)\nโ๏ธุทุฑุญ ุชุนูุถ ุฎูุฏุฑู ูุง ฺฉุงุฑฺฉุฑุฏู\nโ๏ธูุฑูุด ุจู ุตูุฑุช ููุฏ ู ุงูุณุงุท\nโ๏ธุงูุณุงุท ฑฒ ุงู ถฐ ูุงู\nโ๏ธุชุญูู ฒฐ ุฑูุฒู\nโ๏ธุณูุฏ ถ ุฏุงูฺฏ ุจู ูุงู\nโ๏ธุฎุฑุฏ ุจู ุตูุฑุช ุญุถูุฑ ู ุบุฑู ุญุถูุฑ\nโ๏ธุซุจุช ูุงู ุจู ููุฑุงู ุนูุฏ ูุฑุงุฑุฏุงุฏ\n๐จโ๐ผฺฉุงุฑุดูุงุณ ูุฑูุด\nูุตุทู ูุดูุฏ",
    "ฺฉุงุฑฺฉุฑุฏ": "ุตูุฑ ฺฉูููุชุฑ",
    "ููุน ุณูุฎุช": "ุจูุฒู",
    "ฺฏุฑุจฺฉุณ": "ุงุชููุงุชฺฉ",
    "ูุถุนุช ุจุฏูู": "ุจุฏูู ุฑูฺฏ",
    "ุฑูฺฏ ุจุฏูู": "ูุดฺฉ",
    "ุฑูฺฏ ุฏุงุฎู": "ุฏุงุฎู ูุดฺฉ",
    "ุญุฌู ููุชูุฑ": "1.5 ูุชุฑ",
    "ูพุดุฑุงูู": "4 ุณููุฏุฑ",
    "ุดุชุงุจ": "12.5 ุซุงูู",
    "ูุตุฑู ุชุฑฺฉุจ": "6.8 ูุชุฑ ุฏุฑ ุตุฏ ฺฉูููุชุฑ"
  },
  {
    "ูุงู": "ุฏฺฏูุชุ ูพุฑุงู",
    "ุณุงู ุณุงุฎุช": "1403",
    "ูุฏู": "ุงุชููุงุชฺฉ",
    "ุชุงู": "ุฏูุงู ูพุด",
    "ููุช": 2100000000.0,
    "ุขุฏุฑุณ": "ุชูุฑุงู / ุดูุฏ ูุทูุฑ",
    "ุชูุถุญุงุช": " ุชูุถุญุงุช ----- ฺู ููุฏ -----\nูุดุงูุฑ ู ฺฉุงุฑุดูุงุณ ุดูุง : ุฎุงูู ุดุฑู\nโ๏ธุชุญูู ุจู ุฑูุฒ ุจุง ุณูุฏ ู ูุฏุงุฑฺฉ ุขูุงุฏู\nโ๏ธุฎูุฏุฑู ุฎุดฺฉ ุูุงุจู ุฑูุช ุญุถูุฑ\nโ๏ธุญู ฺฉุงุฑุดูุงุณ ูุจู ุงุฒ ุฎุฑุฏ ุจุง ุดูุง\nโ๏ธ ุชูุงู ุฎูุฏุฑููุง ุฏุงุฑุง ฺฏุงุฑุงูุช ูุนุงู ู ุจูู ูุงูู ูุจุงุดุฏ.\nโ๏ธูุงุจู ูุนุงูุถู ",
    "ฺฉุงุฑฺฉุฑุฏ": "ุตูุฑ ฺฉูููุชุฑ",
    "ููุน ุณูุฎุช": "ุจูุฒู",
    "ฺฏุฑุจฺฉุณ": "ุงุชููุงุชฺฉ",
    "ูุถุนุช ุจุฏูู": "ุจุฏูู ุฑูฺฏ",
    "ุฑูฺฏ ุจุฏูู": "ุณูุฏ",
    "ุฑูฺฏ ุฏุงุฎู": "ุฏุงุฎู ูุงุฑูู",
    "ุญุฌู ููุชูุฑ": "1.5 ูุชุฑ",
    "ูพุดุฑุงูู": "4 ุณููุฏุฑ ุชูุฑุจูุดุงุฑฺ (SFG15T)",
    "ุดุชุงุจ": "13 ุซุงูู",
    "ูุตุฑู ุชุฑฺฉุจ": "7.3 ูุชุฑ ุฏุฑ ุตุฏ ฺฉูููุชุฑ"
  },
  {
    "ูุงู": "ฺฉ ุงู ุณุ J7",
    "ุณุงู ุณุงุฎุช": "1404",
    "ูุฏู": "ุงุชููุงุชฺฉ",
    "ุชุงู": "ุฏูุงู ูพุด",
    "ููุช": 1840000000.0,
    "ุขุฏุฑุณ": "ุชูุฑุงู / ุขุฌูุฏุงูู",
    "ุชูุถุญุงุช": " ุชูุถุญุงุช โ๏ธุดุฑุงุท ูุฑูุด ุนุงู\nโ๏ธููุฏ ู ุงูุณุงุท\nโ๏ธููุงูุฏฺฏ ุฑุณู \nโ๏ธุฎุณุฑูุงู\nโ๏ธุซุจุช ูุงู ุชุญูู ฒฐ ุฑูุฒู\nโ๏ธุจุฑุง ุดุฑุงุท ุนุงู ุงูุณุงุท ูุทูุง ุชูุงุณ ุจฺฏุฑุฏ\n๐จโ๐ผฺฉุงุฑุดูุงุณ ูุฑูุด\nูุตุทู ูุดูุฏ",
    "ฺฉุงุฑฺฉุฑุฏ": "ุตูุฑ ฺฉูููุชุฑ",
    "ููุน ุณูุฎุช": "ุจูุฒู",
    "ฺฏุฑุจฺฉุณ": "ุงุชููุงุชฺฉ",
    "ูุถุนุช ุจุฏูู": "ุจุฏูู ุฑูฺฏ",
    "ุฑูฺฏ ุจุฏูู": "ุณูุฏ",
    "ุฑูฺฏ ุฏุงุฎู": "ุฏุงุฎู ูุดฺฉ",
    "ุญุฌู ููุชูุฑ": "1.5 ูุชุฑ",
    "ูพุดุฑุงูู": "4 ุณููุฏุฑ ุชูุฑุจูุดุงุฑฺ TGDi"
  },
  {
    "ูุงู": "ฺฉ ุงู ุณุ T9",
    "ุณุงู ุณุงุฎุช": "1403",
    "ูุฏู": "2 ูุชุฑ ุชูุฑุจู",
    "ุชุงู": "ุฏูุงู ูพุด",
    "ููุช": 2990000000.0,
    "ุขุฏุฑุณ": "ุชูุฑุงู / ุดูุฏ ูุทูุฑ",
    "ุชูุถุญุงุช": " ุชูุถุญุงุช ----- ฺู ููุฏ -----\nูุดุงูุฑ ู ฺฉุงุฑุดูุงุณ ุดูุง : ุฎุงูู ุดุฑู\nโ๏ธุชุญูู ุจู ุฑูุฒ ุจุง ุณูุฏ ู ูุฏุงุฑฺฉ ุขูุงุฏู\nโ๏ธุฎูุฏุฑู ุฎุดฺฉ ุูุงุจู ุฑูุช ุญุถูุฑ\nโ๏ธุญู ฺฉุงุฑุดูุงุณ ูุจู ุงุฒ ุฎุฑุฏ ุจุง ุดูุง\nโ๏ธ ุชูุงู ุฎูุฏุฑููุง ุฏุงุฑุง ฺฏุงุฑุงูุช ูุนุงู ู ุจูู ูุงูู ูุจุงุดุฏ.\nโ๏ธูุงุจู ูุนุงูุถู",
    "ฺฉุงุฑฺฉุฑุฏ": "ุตูุฑ ฺฉูููุชุฑ",
    "ููุน ุณูุฎุช": "ุจูุฒู",
    "ฺฏุฑุจฺฉุณ": "ุงุชููุงุชฺฉ",
    "ูุถุนุช ุจุฏูู": "ุจุฏูู ุฑูฺฏ",
    "ุฑูฺฏ ุจุฏูู": "ุณูุฏ",
    "ุฑูฺฏ ุฏุงุฎู": "ุฏุงุฎู ูุดฺฉ",
    "ุญุฌู ููุชูุฑ": "2.0 ูุชุฑ",
    "ูพุดุฑุงูู": "4 ุณููุฏุฑ ุชูุฑุจูุดุงุฑฺ (HFC4DB2)"
  },
  {
    "ูุงู": "ฺฉ ุงู ุณุ X5",
    "ุณุงู ุณุงุฎุช": "1404",
    "ูุฏู": "1.5 ูุชุฑ ุชูุฑุจู",
    "ุชุงู": "ุฏูุงู ูพุด",
    "ููุช": 1890000000.0,
    "ุขุฏุฑุณ": "ุชูุฑุงู / ูพููฺฉ",
    "ุชูุถุญุงุช": " ุชูุถุญุงุช ^^^^^^^^ููุงูุฏฺฏ ูุฌุงุฒ ฺฉุฑูุงู ููุชูุฑ ฺฉุฏ 1752 ุฑูุน^^^^^^^^\nโฎ๏ธ ุชุญูู 20ุฑูุฒ ฺฉุงุฑ ู ุชุญูู ุฏุฑุจ ฺฉุงุฑุฎุงูู \nโฎ๏ธ ุณูุฏ ุฏุณุชู ุงูู ุจู ูุงู ุดูุง ุฎุฑุฏุงุฑ ูุญุชุฑู \nูุฒุงุง :\nโุตุฑูู ุฌู ุฏุฑ ุฒูุงู ู ูุฒูู\nโุจุฏูู ูุงุณุทู ุูุณุชูู ุงุฒ ูุฑูุดูุฏู\nโุฎุฑุฏ ูุทูุฆู ู ุจุฏูู ุฏุฑุฏุณุฑ\nโุฌูุช ฺฉุณุจ ุงุทูุงุนุงุช ุจุดุชุฑ ุจุงููฺฉุงุฑุงู ูุง ุฏุฑ ุงุฑุชุจุงุท ุจุงุดุฏ",
    "ฺฉุงุฑฺฉุฑุฏ": "ุตูุฑ ฺฉูููุชุฑ",
    "ููุน ุณูุฎุช": "ุจูุฒู",
    "ฺฏุฑุจฺฉุณ": "ุงุชููุงุชฺฉ",
    "ูุถุนุช ุจุฏูู": "ุจุฏูู ุฑูฺฏ",
    "ุฑูฺฏ ุจุฏูู": "ูุดฺฉ",
    "ุฑูฺฏ ุฏุงุฎู": "ุฏุงุฎู ูุดฺฉ",
    "ุญุฌู ููุชูุฑ": "1.5 ูุชุฑ",
    "ูพุดุฑุงูู": "4 ุณููุฏุฑ ุชูุฑุจูุดุงุฑฺ (4GC16D)"
  },
  {
    "ูุงู": "ฺุงูฺฏุงูุ CS 55 ูพูุงุณ",
    "ุณุงู ุณุงุฎุช": "2024",
    "ูุฏู": "1.5 ูุชุฑ ุชูุฑุจู",
    "ุชุงู": "ุฏูุงู ูพุด",
    "ููุช": 2920000000.0,
    "ุขุฏุฑุณ": "ุชูุฑุงู / ุดูุฏ ูุทูุฑ",
    "ุชูุถุญุงุช": " ุชูุถุญุงุช ----- ฺู ููุฏ -----\nูุดุงูุฑ ู ฺฉุงุฑุดูุงุณ ุดูุง : ุฎุงูู ุงููุงุณ\nโ๏ธุชุญูู ุจู ุฑูุฒ ุจุง ุณูุฏ ู ูุฏุงุฑฺฉ ุขูุงุฏู\nโ๏ธุฎูุฏุฑู ุฎุดฺฉ ุูุงุจู ุฑูุช ุญุถูุฑ\nโ๏ธุญู ฺฉุงุฑุดูุงุณ ูุจู ุงุฒ ุฎุฑุฏ ุจุง ุดูุง\nโ๏ธ ุชูุงู ุฎูุฏุฑููุง ุฏุงุฑุง ฺฏุงุฑุงูุช ูุนุงู ู ุจูู ูุงูู ูุจุงุดุฏ.\nโ๏ธูุงุจู ูุนุงูุถู ",
    "ฺฉุงุฑฺฉุฑุฏ": "ุตูุฑ ฺฉูููุชุฑ",
    "ููุน ุณูุฎุช": "ุจูุฒู",
    "ฺฏุฑุจฺฉุณ": "ุงุชููุงุชฺฉ",
    "ูุถุนุช ุจุฏูู": "ุจุฏูู ุฑูฺฏ",
    "ุฑูฺฏ ุจุฏูู": "ุณูุฏ",
    "ุฑูฺฏ ุฏุงุฎู": "ุฏุงุฎู ูุดฺฉ",
    "ุญุฌู ููุชูุฑ": "1.5 ูุชุฑ",
    "ูพุดุฑุงูู": "4 ุณููุฏุฑ ุชูุฑุจูุดุงุฑฺ (JL473ZQ7)",
    "ูุตุฑู ุชุฑฺฉุจ": "6.6 ูุชุฑ ุฏุฑ ุตุฏ ฺฉูููุชุฑ"
  },
  {
    "ูุงู": "ุฑุณูพฺฉุชุ ูพุฑุงู",
    "ุณุงู ุณุงุฎุช": "1403",
    "ูุฏู": "ุชูพ 2",
    "ุชุงู": "ุฏูุงู ูพุด",
    "ููุช": 1770000000.0,
    "ุขุฏุฑุณ": "ุชูุฑุงู / ุดูุฏ ูุทูุฑ",
    "ุชูุถุญุงุช": " ุชูุถุญุงุช ----- ฺู ููุฏ -----\nูุดุงูุฑ ู ฺฉุงุฑุดูุงุณ ุดูุง : ุฎุงูู ุดุฑู\nโ๏ธุชุญูู ุจู ุฑูุฒ ุจุง ุณูุฏ ู ูุฏุงุฑฺฉ ุขูุงุฏู\nโ๏ธุฎูุฏุฑู ุฎุดฺฉ ุูุงุจู ุฑูุช ุญุถูุฑ\nโ๏ธุญู ฺฉุงุฑุดูุงุณ ูุจู ุงุฒ ุฎุฑุฏ ุจุง ุดูุง\nโ๏ธ ุชูุงู ุฎูุฏุฑููุง ุฏุงุฑุง ฺฏุงุฑุงูุช ูุนุงู ู ุจูู ูุงูู ูุจุงุดุฏ.\nโ๏ธูุงุจู ูุนุงูุถู ",
    "ฺฉุงุฑฺฉุฑุฏ": "ุตูุฑ ฺฉูููุชุฑ",
    "ููุน ุณูุฎุช": "ุจูุฒู",
    "ฺฏุฑุจฺฉุณ": "ุงุชููุงุชฺฉ",
    "ูุถุนุช ุจุฏูู": "ุจุฏูู ุฑูฺฏ",
    "ุฑูฺฏ ุจุฏูู": "ุณูุฏ",
    "ุฑูฺฏ ุฏุงุฎู": "ุฏุงุฎู ูุดฺฉ",
    "ุญุฌู ููุชูุฑ": "1.5 ูุชุฑ",
    "ูพุดุฑุงูู": "4 ุณููุฏุฑ ุชูุฑุจูุดุงุฑฺ (4T15C)",
    "ุดุชุงุจ": "10.5 ุซุงูู",
    "ูุตุฑู ุชุฑฺฉุจ": "7.5 ูุชุฑ ุฏุฑ ุตุฏ ฺฉูููุชุฑ"
  },
  {
    "ูุงู": "ูพฺูุ 207",
    "ุณุงู ุณุงุฎุช": "1404",
    "ูุฏู": "ุงุชููุงุชฺฉ TU5P",
    "ุชุงู": "ุฏูุงู ูพุด",
    "ููุช": "ุชูุงูู",
    "ุขุฏุฑุณ": "ุชูุฑุงู / ุงูุฏุฑุฒฺฏู",
    "ุชูุถุญุงุช": " ุชูุถุญุงุช โุงูุฏ ฺฏุงูุฑ\nุจุด ุงุฒ ฑต ุณุงู ุณุงุจูู ุฏุฑ ุฎุฑุฏ ู ูุฑูุด ูุงุดู\nุนุถู ุฑุณู ุงุชุญุงุฏู\nุชุญูู ููุฑ ุจุง ุงูฺฉุงู ฺฉุงุฑุดูุงุณ\nโููุช ุขุฎุฑ ุฑุง ุงุฒ ูุง ุจุฎูุงูุฏ",
    "ฺฉุงุฑฺฉุฑุฏ": "ุตูุฑ ฺฉูููุชุฑ",
    "ููุน ุณูุฎุช": "ุจูุฒู",
    "ฺฏุฑุจฺฉุณ": "ุงุชููุงุชฺฉ",
    "ูุถุนุช ุจุฏูู": "ุจุฏูู ุฑูฺฏ",
    "ุฑูฺฏ ุจุฏูู": "ุณูุฏ",
    "ุฑูฺฏ ุฏุงุฎู": "ุฏุงุฎู ูุดฺฉ",
    "ุญุฌู ููุชูุฑ": "1.6 ูุชุฑ",
    "ูพุดุฑุงูู": "4 ุณููุฏุฑ TU5P",
    "ุดุชุงุจ": "12.6 ุซุงูู",
    "ูุตุฑู ุชุฑฺฉุจ": "7.4 ูุชุฑ ุฏุฑ ุตุฏ ฺฉูููุชุฑ"
  },
  {
    "ูุงู": "ูููฺฉุณุ FX",
    "ุณุงู ุณุงุฎุช": "1402",
    "ูุฏู": "ูพุฑููู FWD",
    "ุชุงู": "ุฏูุงู ูพุด",
    "ููุช": 2400000000.0,
    "ุขุฏุฑุณ": "ุงุตููุงู / ุขุฐุฑ",
    "ุชูุถุญุงุช": "",
    "ฺฉุงุฑฺฉุฑุฏ": "ุตูุฑ ฺฉูููุชุฑ",
    "ููุน ุณูุฎุช": "ุจูุฒู",
    "ฺฏุฑุจฺฉุณ": "ุงุชููุงุชฺฉ",
    "ูุถุนุช ุจุฏูู": "ุจุฏูู ุฑูฺฏ",
    "ุฑูฺฏ ุจุฏูู": "ูุดฺฉ",
    "ุฑูฺฏ ุฏุงุฎู": "ุฏุงุฎู ูุดฺฉ",
    "ุญุฌู ููุชูุฑ": "1.6 ูุชุฑ",
    "ูพุดุฑุงูู": "4 ุณููุฏุฑ ุชูุฑุจูุดุงุฑฺ (4J16)",
    "ุดุชุงุจ": "8 ุซุงูู",
    "ูุตุฑู ุชุฑฺฉุจ": "6.8 ูุชุฑ ุฏุฑ ุตุฏ ฺฉูููุชุฑ"
  },
  {
    "ูุงู": "ฺฉ ุงู ุณุ ุงฺฏู",
    "ุณุงู ุณุงุฎุช": "1404",
    "ูุฏู": "1.5 ูุชุฑ",
    "ุชุงู": "ุฏูุงู ูพุด",
    "ููุช": 1050000000.0,
    "ุขุฏุฑุณ": "ุชูุฑุงู / ูพุฑูุฒ",
    "ุชูุถุญุงุช": " ุชูุถุญุงุช โญโญ ููุงูุฏฺฏ ูุฌุงุฒ ฺฉุฑูุงู ููุชูุฑ ฺฉุฏ 1762 ุฑูุน ูุงโญโญ\nุณูุฏ ุงุฒุงุฏ ู ูุงุจู ุงูุชูุงู\nุชุญูู ููุฑ\nุฌูุช ุฎุฑุฏ ู ุจุงุฒุฏุฏ ุฎูุฏุฑูุชูุงุณ ุจฺฏุฑุฏ",
    "ฺฉุงุฑฺฉุฑุฏ": "ุตูุฑ ฺฉูููุชุฑ",
    "ููุน ุณูุฎุช": "ุจูุฒู",
    "ฺฏุฑุจฺฉุณ": "ุงุชููุงุชฺฉ",
    "ูุถุนุช ุจุฏูู": "ุจุฏูู ุฑูฺฏ",
    "ุฑูฺฏ ุจุฏูู": "ูุดฺฉ",
    "ุฑูฺฏ ุฏุงุฎู": "ุฏุงุฎู ูุดฺฉ",
    "ุญุฌู ููุชูุฑ": "1.5 ูุชุฑ",
    "ูพุดุฑุงูู": "4 ุณููุฏุฑ",
    "ุดุชุงุจ": "12.5 ุซุงูู",
    "ูุตุฑู ุชุฑฺฉุจ": "6.8 ูุชุฑ ุฏุฑ ุตุฏ ฺฉูููุชุฑ"
  },
  {
    "ูุงู": "ฺฉ ุงู ุณุ J7",
    "ุณุงู ุณุงุฎุช": "1403",
    "ูุฏู": "ุงุชููุงุชฺฉ",
    "ุชุงู": "ุฏูุงู ูพุด",
    "ููุช": 1930000000.0,
    "ุขุฏุฑุณ": "ุชูุฑุงู / ุดูุฏ ูุทูุฑ",
    "ุชูุถุญุงุช": " ุชูุถุญุงุช ----- ฺู ููุฏ -----\nูุดุงูุฑ ู ฺฉุงุฑุดูุงุณ ุดูุง : ุฎุงูู ุงููุงุณ\nโ๏ธุชุญูู ุจู ุฑูุฒ ุจุง ุณูุฏ ู ูุฏุงุฑฺฉ ุขูุงุฏู\nโ๏ธุฎูุฏุฑู ุฎุดฺฉ ุูุงุจู ุฑูุช ุญุถูุฑ\nโ๏ธุญู ฺฉุงุฑุดูุงุณ ูุจู ุงุฒ ุฎุฑุฏ ุจุง ุดูุง\nโ๏ธ ุชูุงู ุฎูุฏุฑููุง ุฏุงุฑุง ฺฏุงุฑุงูุช ูุนุงู ู ุจูู ูุงูู ูุจุงุดุฏ.\nโ๏ธูุงุจู ูุนุงูุถู ",
    "ฺฉุงุฑฺฉุฑุฏ": "ุตูุฑ ฺฉูููุชุฑ",
    "ููุน ุณูุฎุช": "ุจูุฒู",
    "ฺฏุฑุจฺฉุณ": "ุงุชููุงุชฺฉ",
    "ูุถุนุช ุจุฏูู": "ุจุฏูู ุฑูฺฏ",
    "ุฑูฺฏ ุจุฏูู": "ูุดฺฉ",
    "ุฑูฺฏ ุฏุงุฎู": "ุฏุงุฎู ูุดฺฉ",
    "ุญุฌู ููุชูุฑ": "1.5 ูุชุฑ",
    "ูพุดุฑุงูู": "4 ุณููุฏุฑ ุชูุฑุจูุดุงุฑฺ TGDi"
  },
  {
    "ูุงู": "ูุฏูุชุ ูพุฑุงู",
    "ุณุงู ุณุงุฎุช": "1403",
    "ูุฏู": "ุชูพ 2 ููุช ููุฑู",
    "ุชุงู": "ุฏูุงู ูพุด",
    "ููุช": 2270000000.0,
    "ุขุฏุฑุณ": "ุชูุฑุงู / ุดูุฏ ูุทูุฑ",
    "ุชูุถุญุงุช": " ุชูุถุญุงุช ----- ฺู ููุฏ -----\nูุดุงูุฑ ู ฺฉุงุฑุดูุงุณ ุดูุง : ุฎุงูู ุดุฑู\nโ๏ธุชุญูู ุจู ุฑูุฒ ุจุง ุณูุฏ ู ูุฏุงุฑฺฉ ุขูุงุฏู\nโ๏ธุฎูุฏุฑู ุฎุดฺฉ ุูุงุจู ุฑูุช ุญุถูุฑ\nโ๏ธุญู ฺฉุงุฑุดูุงุณ ูุจู ุงุฒ ุฎุฑุฏ ุจุง ุดูุง\nโ๏ธ ุชูุงู ุฎูุฏุฑููุง ุฏุงุฑุง ฺฏุงุฑุงูุช ูุนุงู ู ุจูู ูุงูู ูุจุงุดุฏ.\nโ๏ธูุงุจู ูุนุงูุถู ",
    "ฺฉุงุฑฺฉุฑุฏ": "ุตูุฑ ฺฉูููุชุฑ",
    "ููุน ุณูุฎุช": "ุจูุฒู",
    "ฺฏุฑุจฺฉุณ": "ุงุชููุงุชฺฉ",
    "ูุถุนุช ุจุฏูู": "ุจุฏูู ุฑูฺฏ",
    "ุฑูฺฏ ุจุฏูู": "ูุดฺฉ",
    "ุฑูฺฏ ุฏุงุฎู": "ุฏุงุฎู ูุดฺฉ",
    "ุญุฌู ููุชูุฑ": "1.5 ูุชุฑ",
    "ูพุดุฑุงูู": "4 ุณููุฏุฑ ุชูุฑุจูุดุงุฑฺ (4T15C)",
    "ุดุชุงุจ": "11.9 ุซุงูู",
    "ูุตุฑู ุชุฑฺฉุจ": "8.1 ูุชุฑ ุฏุฑ ุตุฏ ฺฉูููุชุฑ"
  },
  {
    "ูุงู": "ฺฉ ุงู ุณุ X5",
    "ุณุงู ุณุงุฎุช": "1403",
    "ูุฏู": "1.5 ูุชุฑ ุชูุฑุจู",
    "ุชุงู": "ุฏูุงู ูพุด",
    "ููุช": 1940000000.0,
    "ุขุฏุฑุณ": "ุชูุฑุงู / ุดูุฏ ูุทูุฑ",
    "ุชูุถุญุงุช": " ุชูุถุญุงุช ----- ฺู ููุฏ -----\nูุดุงูุฑ ู ฺฉุงุฑุดูุงุณ ุดูุง : ุฎุงูู ุงููุงุณ\nโ๏ธุชุญูู ุจู ุฑูุฒ ุจุง ุณูุฏ ู ูุฏุงุฑฺฉ ุขูุงุฏู\nโ๏ธุฎูุฏุฑู ุฎุดฺฉ ุูุงุจู ุฑูุช ุญุถูุฑ\nโ๏ธุญู ฺฉุงุฑุดูุงุณ ูุจู ุงุฒ ุฎุฑุฏ ุจุง ุดูุง\nโ๏ธ ุชูุงู ุฎูุฏุฑููุง ุฏุงุฑุง ฺฏุงุฑุงูุช ูุนุงู ู ุจูู ูุงูู ูุจุงุดุฏ.\nโ๏ธูุงุจู ูุนุงูุถู",
    "ฺฉุงุฑฺฉุฑุฏ": "ุตูุฑ ฺฉูููุชุฑ",
    "ููุน ุณูุฎุช": "ุจูุฒู",
    "ฺฏุฑุจฺฉุณ": "ุงุชููุงุชฺฉ",
    "ูุถุนุช ุจุฏูู": "ุจุฏูู ุฑูฺฏ",
    "ุฑูฺฏ ุจุฏูู": "ุณูุฏ",
    "ุฑูฺฏ ุฏุงุฎู": "ุฏุงุฎู ูุดฺฉ",
    "ุญุฌู ููุชูุฑ": "1.5 ูุชุฑ",
    "ูพุดุฑุงูู": "4 ุณููุฏุฑ ุชูุฑุจูุดุงุฑฺ (4GC16D)"
  },
  {
    "ูุงู": "ูพฺูุ 207",
    "ุณุงู ุณุงุฎุช": "1403",
    "ูุฏู": "ูพุงููุฑุงูุง ุงุชููุงุชฺฉ TU5P",
    "ุชุงู": "ุฏูุงู ูพุด",
    "ููุช": 1140000000.0,
    "ุขุฏุฑุณ": "ุชูุฑุงู / ุจุงุบ ูุถ",
    "ุชูุถุญุงุช": " ุชูุถุญุงุช ุจูู ุซุงูุซ ุชุง ฑดฐด.ฑฑ.ฑท\n ุฎุดฺฉ",
    "ฺฉุงุฑฺฉุฑุฏ": "ุตูุฑ ฺฉูููุชุฑ",
    "ููุน ุณูุฎุช": "ุจูุฒู",
    "ฺฏุฑุจฺฉุณ": "ุงุชููุงุชฺฉ",
    "ูุถุนุช ุจุฏูู": "ุจุฏูู ุฑูฺฏ",
    "ุฑูฺฏ ุจุฏูู": "ุณูุฏ",
    "ุฑูฺฏ ุฏุงุฎู": "ุฏุงุฎู ูุดฺฉ"
  },
  {
    "ูุงู": "ฺฉ ุงู ุณุ T8",
    "ุณุงู ุณุงุฎุช": "1404",
    "ูุฏู": "ุฏูุฏู ุง",
    "ุชุงู": "ุฏูุงู ูพุด",
    "ููุช": 1010000000.0,
    "ุขุฏุฑุณ": "ุชูุฑุงู / 17 ุดูุฑูุฑ",
    "ุชูุถุญุงุช": " ุชูุถุญุงุช โููุงูุฏฺฏ ูุฌุงุฒ ฺฉุฑูุงู ููุชูุฑ โ\nโชโชโชโชโชโชโชโชโชโชโชโชโชโชโชโชโชโชโชโชโชโชโชโชโชโชโชโชโช Rafiee Motor โชโชโชโชโชโชโชโชโชโชโชโชโชโชโชโชโชโชโชโชโชโชโชโชโชโชโชโชโชโช\nโฌโปโพ ุขุบุงุฒ ุซุจุช ูุงู ุงูุณุงุท ุจุง ูพุด ูพุฑุฏุงุฎุช ุจู ูุจูุบ ุฏุฑุฌ ุดุฏู โพโปโฌ\nโุงูุชุฎุงุจ ุฑูฺฏ ุจู ุงูุชุฎุงุจ ูุชูุงุถ : ุณูุฏุ ูุดฺฉุ ุขุจุ ูุฑูุฒ\nโุฏุงุฑุง ุจูู ุจุฏูู ุชุง ูพุงุงู ุงูุณุงุท \nโุงูุณุงุท 12 ูุงู ู 24 ูุงู \nโุธุฑูุช ู ูููุช ูุญุฏูุฏ โ\nโุจุฑุง ุงุทูุงุนุงุช ุจุดุชุฑ ุจุง ฺฉุงุฑุดูุงุณุงู ูุง ุฏุฑ ุงุฑุชุจุงุท ุจุงุดุฏ โ",
    "ฺฉุงุฑฺฉุฑุฏ": "ุตูุฑ ฺฉูููุชุฑ",
    "ููุน ุณูุฎุช": "ุจูุฒู",
    "ฺฏุฑุจฺฉุณ": "ุฏูุฏู ุง",
    "ูุถุนุช ุจุฏูู": "ุจุฏูู ุฑูฺฏ",
    "ุฑูฺฏ ุจุฏูู": "ุณูุฏ",
    "ุฑูฺฏ ุฏุงุฎู": "ุฏุงุฎู ูุดฺฉ"
  },
  {
    "ูุงู": "ุฑููุ ุชูุฏุฑ 90",
    "ุณุงู ุณุงุฎุช": "1390",
    "ูุฏู": "E2",
    "ุชุงู": "ุฏูุงู ูพุด",
    "ููุช": 440000000.0,
    "ุขุฏุฑุณ": "ุงููุงุฒ / ูุฑููฺฏ ุดูุฑ",
    "ุชูุถุญุงุช": " ุชูุถุญุงุช ุจุง ุณูุงู.\nูุงุดู ฺฉุงููุง ุฎููฺฏ ู ฺฉู ฺฉุงุฑฺฉุฑุฏ\nููุชูุฑุ ฺฏุฑุจฺฉุณ ู ฺฉููุฑ ฺฉุงููุงู ุณุงูู - ุฏุงุฎู ฺฉุงุจู ู ุฑุฎ ูุงุดู ุนุงู\nุณูุฏ ุชฺฉ ุจุฑฺฏ\nููุช ุจุฑ ูุจูุง ุฏูุฑ ุฑูฺฏ ฺฉุงูู ุงุนูุงู ฺฉุฑุฏู ูู ุญุฏูุฏ 50 ุฏุฑุตุฏ ุฑูฺฏ ุฏุงุฑุฏ\nูุฑูุด ููุท ุจู ูุตุฑู ฺฉููุฏู ู ุจู ุดุฑุท ุชุนูุถ ูพูุงฺฉ ููุฑ\nุจุงุฒุฏุฏ ุงุฒ ุณุงุนุช 7 ุชุง 17 ุจุง ููุงููฺฏ",
    "ฺฉุงุฑฺฉุฑุฏ": "97,000 km",
    "ููุน ุณูุฎุช": "ุจูุฒู",
    "ฺฏุฑุจฺฉุณ": "ุฏูุฏู ุง",
    "ูุถุนุช ุจุฏูู": "ุฏูุฑ ุฑูฺฏ",
    "ุฑูฺฏ ุจุฏูู": "ููุฑู ุง",
    "ุฑูฺฏ ุฏุงุฎู": "ุฏุงุฎู ูุดฺฉ",
    "ุญุฌู ููุชูุฑ": "1.6 ูุชุฑ",
    "ูพุดุฑุงูู": "4 ุณููุฏุฑ",
    "ุดุชุงุจ": "10.2 ุซุงูู",
    "ูุตุฑู ุชุฑฺฉุจ": "6.9 ูุชุฑ ุฏุฑ ุตุฏ ฺฉูููุชุฑ"
  },
  {
    "ูุงู": "ุงู ู ุงูุ X55 PRO",
    "ุณุงู ุณุงุฎุช": "1403",
    "ูุฏู": "IE",
    "ุชุงู": "ุฏูุงู ูพุด",
    "ููุช": 1890000000.0,
    "ุขุฏุฑุณ": "ุชูุฑุงู / ุญุณูโุขุจุงุฏ",
    "ุชูุถุญุงุช": " ุชูุถุญุงุช ูุฏุงุฑฺฉ ฺฉุงูู ู ุขูุงุฏู ุงูุชูุงู",
    "ฺฉุงุฑฺฉุฑุฏ": "ุตูุฑ ฺฉูููุชุฑ",
    "ููุน ุณูุฎุช": "ุจูุฒู",
    "ฺฏุฑุจฺฉุณ": "ุงุชููุงุชฺฉ",
    "ูุถุนุช ุจุฏูู": "ุจุฏูู ุฑูฺฏ",
    "ุฑูฺฏ ุจุฏูู": "ูุดฺฉ",
    "ุฑูฺฏ ุฏุงุฎู": "ุฏุงุฎู ูุดฺฉ",
    "ุญุฌู ููุชูุฑ": "1.5 ูุชุฑ",
    "ูพุดุฑุงูู": "4 ุณููุฏุฑ ุชูุฑุจูุดุงุฑฺ ุจููู ุดุฏู"
  },
  {
    "ูุงู": "ุฌฺฉุ S3",
    "ุณุงู ุณุงุฎุช": "1403",
    "ูุฏู": "ุงุชููุงุชฺฉ",
    "ุชุงู": "ุฏูุงู ูพุด",
    "ููุช": 1100000000.0,
    "ุขุฏุฑุณ": "ุชูุฑุงู / 17 ุดูุฑูุฑ",
    "ุชูุถุญุงุช": " ุชูุถุญุงุช ๐ดููุงูุฏฺฏ ูุฌุงุฒ ฺฉุฑูุงู ููุชูุฑ ุฑูุน ูุง๐ด\nุดุฑุงุท ูุฑูุด ููุฏ ู ุงูุณุงุท:\nโุงูุณุงุท : 12 ุงู 18 ูุงูู\nโุจุฏูู ุถุงูู _ ููุท ุจุง ฺฺฉ ุตุงุฏ\nโุณูุฏ ุจู ูุงู ุฎุฑุฏุงุฑ | ุชุญูู 60 ุฑูุฒู ฺฉุงุฑ\nูุฒุงุง :\nโุตุฑูู ุฌู ุฏุฑ ุฒูุงู ู ูุฒูู\nโุจุฏูู ูุงุณุทู ุูุณุชูู ุงุฒ ฺฉุงุฑุฎุงูู\nโุฎุฑุฏ ูุทูุฆู ู ุจุฏูู ุฏุฑุฏุณุฑ\nโุฌูุช ฺฉุณุจ ุงุทูุงุนุงุช ุจุดุชุฑ ุจุงููฺฉุงุฑุงู ูุง ุฏุฑ ุงุฑุชุจุงุท ุจุงุดุฏ.",
    "ฺฉุงุฑฺฉุฑุฏ": "ุตูุฑ ฺฉูููุชุฑ",
    "ููุน ุณูุฎุช": "ุจูุฒู",
    "ฺฏุฑุจฺฉุณ": "ุงุชููุงุชฺฉ",
    "ูุถุนุช ุจุฏูู": "ุจุฏูู ุฑูฺฏ",
    "ุฑูฺฏ ุจุฏูู": "ุณูุฏ",
    "ุฑูฺฏ ุฏุงุฎู": "ุฏุงุฎู ูุดฺฉ",
    "ุญุฌู ููุชูุฑ": "1.6 ูุชุฑ",
    "ูพุดุฑุงูู": "4 ุณููุฏุฑ",
    "ุดุชุงุจ": "10.8 ุซุงูู",
    "ูุตุฑู ุชุฑฺฉุจ": "7.6 ูุชุฑ ุฏุฑ ุตุฏ ฺฉูููุชุฑ"
  },
  {
    "ูุงู": "ฺฉ ุงู ุณุ T9",
    "ุณุงู ุณุงุฎุช": "1404",
    "ูุฏู": "2 ูุชุฑ ุชูุฑุจู",
    "ุชุงู": "ุฏูุงู ูพุด",
    "ููุช": 2750000000.0,
    "ุขุฏุฑุณ": "ุชูุฑุงู / 17 ุดูุฑูุฑ",
    "ุชูุถุญุงุช": " ุชูุถุญุงุช ๐ููุงูุฏฺฏ ฺฉุฑูุงู ููุชูุฑ๐\nโชโชโชโชโชโชโชโชโชโชโชโชโชโชโชโชโชโชโชโชโชโชโชโชRafiee Motorโชโชโชโชโชโชโชโชโชโชโชโชโชโชโชโชโชโชโชโชโชโชโชโช\nโุซุจุช ุชูุงู ุงุณูุงุฏ ุจู ูุงู ูุชูุงุถ \nโุชุญูู ฒฐ ุฑูุฒ ฺฉุงุฑ ุงุฒ ููุงูุฏฺฏ ุฑุณู \nโุฏุงุฑุง ฺฏุงุฑุงูุช ุดุฑฺฉุช \nโูุฑุตุช ููุงุณุจ ุจุฑุง ุณุฑูุงู ฺฏุฐุงุฑ ุจุง ุชุนุฏุงุฏ ูุญุฏูุฏ \nโุนูุฏ ูุฑุงุฑุฏุงุฏ ุฏุฑ ููุงูุฏฺฏ ุฑุณู\nโพโปโพโปโพโปโพโปโพโปโพโปโพโปโพโปโพโปโพโปโพโปโพโปโพโปโพโปโพโปโพโปโพโปโพ\nโุฌูุช ุงุทูุงุนุงุช ุจุดุชุฑ ุจุง ูุง ุชูุงุณ ุจฺฏุฑุฏ.",
    "ฺฉุงุฑฺฉุฑุฏ": "ุตูุฑ ฺฉูููุชุฑ",
    "ููุน ุณูุฎุช": "ุจูุฒู",
    "ฺฏุฑุจฺฉุณ": "ุงุชููุงุชฺฉ",
    "ูุถุนุช ุจุฏูู": "ุจุฏูู ุฑูฺฏ",
    "ุฑูฺฏ ุจุฏูู": "ูุดฺฉ",
    "ุฑูฺฏ ุฏุงุฎู": "ุฏุงุฎู ูุดฺฉ",
    "ุญุฌู ููุชูุฑ": "2.0 ูุชุฑ",
    "ูพุดุฑุงูู": "4 ุณููุฏุฑ ุชูุฑุจูุดุงุฑฺ (HFC4DB2)"
  },
  {
    "ูุงู": "ฺฉ ุงู ุณุ T9",
    "ุณุงู ุณุงุฎุช": "1404",
    "ูุฏู": "2 ูุชุฑ ุชูุฑุจู",
    "ุชุงู": "ุฏูุงู ูพุด",
    "ููุช": 2750000000.0,
    "ุขุฏุฑุณ": "ุชูุฑุงู / ูพุฑูุฒ",
    "ุชูุถุญุงุช": " ุชูุถุญุงุช โญโญ ููุงูุฏฺฏ ูุฌุงุฒ ฺฉุฑูุงู ููุชูุฑ ฺฉุฏ 1762 ุฑูุน ูุงโญโญ\nุณูุฏ ุงุฒุงุฏ ู ูุงุจู ุงูุชูุงู\nุชุญูู ููุฑ\nุฌูุช ุฎุฑุฏ ู ุจุงุฒุฏุฏ ุฎูุฏุฑูุชูุงุณ ุจฺฏุฑุฏ",
    "ฺฉุงุฑฺฉุฑุฏ": "ุตูุฑ ฺฉูููุชุฑ",
    "ููุน ุณูุฎุช": "ุจูุฒู",
    "ฺฏุฑุจฺฉุณ": "ุงุชููุงุชฺฉ",
    "ูุถุนุช ุจุฏูู": "ุจุฏูู ุฑูฺฏ",
    "ุฑูฺฏ ุจุฏูู": "ูุดฺฉ",
    "ุฑูฺฏ ุฏุงุฎู": "ุฏุงุฎู ูุดฺฉ",
    "ุญุฌู ููุชูุฑ": "2.0 ูุชุฑ",
    "ูพุดุฑุงูู": "4 ุณููุฏุฑ ุชูุฑุจูุดุงุฑฺ (HFC4DB2)"
  },
  {
    "ูุงู": "ูููฺฉุณุ ุชฺฏู 7 ูพุฑู",
    "ุณุงู ุณุงุฎุช": "1403",
    "ูุฏู": "ูพุฑููู",
    "ุชุงู": "ุฏูุงู ูพุด",
    "ููุช": 2420000000.0,
    "ุขุฏุฑุณ": "ุชูุฑุงู / ุดูุฏ ูุทูุฑ",
    "ุชูุถุญุงุช": " ุชูุถุญุงุช ----- ฺู ููุฏ -----\nูุดุงูุฑ ู ฺฉุงุฑุดูุงุณ ุดูุง : ุฎุงูู ุตุงุฏู\nโ๏ธุชุญูู ุจู ุฑูุฒ ุจุง ุณูุฏ ู ูุฏุงุฑฺฉ ุขูุงุฏู\nโ๏ธุฎูุฏุฑู ุฎุดฺฉ ุูุงุจู ุฑูุช ุญุถูุฑ\nโ๏ธุญู ฺฉุงุฑุดูุงุณ ูุจู ุงุฒ ุฎุฑุฏ ุจุง ุดูุง\nโ๏ธ ุชูุงู ุฎูุฏุฑููุง ุฏุงุฑุง ฺฏุงุฑุงูุช ูุนุงู ู ุจูู ูุงูู ูุจุงุดุฏ.\nโ๏ธูุงุจู ูุนุงูุถู ",
    "ฺฉุงุฑฺฉุฑุฏ": "ุตูุฑ ฺฉูููุชุฑ",
    "ููุน ุณูุฎุช": "ุจูุฒู",
    "ฺฏุฑุจฺฉุณ": "ุงุชููุงุชฺฉ",
    "ูุถุนุช ุจุฏูู": "ุจุฏูู ุฑูฺฏ",
    "ุฑูฺฏ ุจุฏูู": "ูุดฺฉ",
    "ุฑูฺฏ ุฏุงุฎู": "ุฏุงุฎู ูุดฺฉ",
    "ุญุฌู ููุชูุฑ": "1.5 ูุชุฑ",
    "ูพุดุฑุงูู": "4 ุณููุฏุฑ ุชูุฑุจู ุดุงุฑฺ",
    "ูุตุฑู ุชุฑฺฉุจ": "8.4 ูุชุฑ ุฏุฑ ุตุฏ ฺฉูููุชุฑ"
  },
  {
    "ูุงู": "ฺุงูฺฏุงูุ CS 55 ูพูุงุณ",
    "ุณุงู ุณุงุฎุช": "2024",
    "ูุฏู": "1.5 ูุชุฑ ุชูุฑุจู",
    "ุชุงู": "ุฏูุงู ูพุด",
    "ููุช": "ุชูุงูู",
    "ุขุฏุฑุณ": "ุชูุฑุงู / ูุฑุฏุงูุงุฏ",
    "ุชูุถุญุงุช": " ุชูุถุญุงุช โซ๏ธุดูุงุฑู ุซุจุช (ถฒนถฑฐ) ู ุฏุงุฑุง ุดูุงุณู ูู โซ๏ธูพุฑุฏุงุฎุช ูุฌู ุฏุฑุจ ููุฒู ูพุณ ุงุฒ ุชุงุฏ ฺฉุงุฑุดูุงุณ ูุฏ ูุธุฑ ุดูุง โซ๏ธฺฉ ุณุงู ุจูู ุดุฎุต ุซุงูุซุฺฏุงุฑุงูุช ฺฉุงูู ุดุฑฺฉุช ู ูุนุงู โซ๏ธุณูุฏ ุขุฒุงุฏ โซ๏ธูุฒูู ุงูุชูุงู ุณูุฏ ุจุนูุฏู ูุฌููุนู โซ๏ธุณุงุนุช ฺฉุงุฑ | ธ~ูขู|",
    "ฺฉุงุฑฺฉุฑุฏ": "ุตูุฑ ฺฉูููุชุฑ",
    "ููุน ุณูุฎุช": "ุจูุฒู",
    "ฺฏุฑุจฺฉุณ": "ุงุชููุงุชฺฉ",
    "ูุถุนุช ุจุฏูู": "ุจุฏูู ุฑูฺฏ",
    "ุฑูฺฏ ุจุฏูู": "ุณูุฏ",
    "ุฑูฺฏ ุฏุงุฎู": "ุฏุงุฎู ูุดฺฉ",
    "ุญุฌู ููุชูุฑ": "1.5 ูุชุฑ",
    "ูพุดุฑุงูู": "4 ุณููุฏุฑ ุชูุฑุจูุดุงุฑฺ (JL473ZQ7)",
    "ูุตุฑู ุชุฑฺฉุจ": "6.6 ูุชุฑ ุฏุฑ ุตุฏ ฺฉูููุชุฑ"
  },
  {
    "ูุงู": "ุงฺฉุณุชุฑูุ VX",
    "ุณุงู ุณุงุฎุช": "1403",
    "ูุฏู": "2.0 ูุชุฑ ุชูุฑุจู",
    "ุชุงู": "ุฏูุงู ูพุด",
    "ููุช": "ุชูุงูู",
    "ุขุฏุฑุณ": "ุชูุฑุงู / ูุฑุฏุงูุงุฏ",
    "ุชูุถุญุงุช": " ุชูุถุญุงุช โซ๏ธุดูุงุฑู ุซุจุช (ถฒนถฑฐ) ู ุฏุงุฑุง ุดูุงุณู ูู โซ๏ธูพุฑุฏุงุฎุช ูุฌู ุฏุฑุจ ููุฒู ูพุณ ุงุฒ ุชุงุฏ ฺฉุงุฑุดูุงุณ ูุฏ ูุธุฑ ุดูุง โซ๏ธฺฉ ุณุงู ุจูู ุดุฎุต ุซุงูุซุฺฏุงุฑุงูุช ฺฉุงูู ุดุฑฺฉุช ู ูุนุงู โซ๏ธุณูุฏ ุขุฒุงุฏ โซ๏ธูุฒูู ุงูุชูุงู ุณูุฏ ุจุนูุฏู ูุฌููุนู โซ๏ธุณุงุนุช ฺฉุงุฑ | ธ~ูขู|",
    "ฺฉุงุฑฺฉุฑุฏ": "ุตูุฑ ฺฉูููุชุฑ",
    "ููุน ุณูุฎุช": "ุจูุฒู",
    "ฺฏุฑุจฺฉุณ": "ุงุชููุงุชฺฉ",
    "ูุถุนุช ุจุฏูู": "ุจุฏูู ุฑูฺฏ",
    "ุฑูฺฏ ุจุฏูู": "ูุดฺฉ",
    "ุฑูฺฏ ุฏุงุฎู": "ุฏุงุฎู ูุดฺฉ",
    "ุญุฌู ููุชูุฑ": "2.0 ูุชุฑ",
    "ูพุดุฑุงูู": "4 ุณููุฏุฑ ุชูุฑุจูุดุงุฑฺ (4J20)",
    "ุดุชุงุจ": "9 ุซุงูู"
  },
  {
    "ูุงู": "ูพฺูุ 207",
    "ุณุงู ุณุงุฎุช": "1404",
    "ูุฏู": "ูพุงููุฑุงูุง ุฏูุฏู ุง",
    "ุชุงู": "ุฏูุงู ูพุด",
    "ููุช": "ุชูุงูู",
    "ุขุฏุฑุณ": "ุชูุฑุงู / ูุฑุฏุงูุงุฏ",
    "ุชูุถุญุงุช": " ุชูุถุญุงุช โซ๏ธุดูุงุฑู ุซุจุช (ถฒนถฑฐ) ู ุฏุงุฑุง ุดูุงุณู ูู โโ (ุจุฏูู ฺฉูุณูู ู ฺฉุงุฑูุฒุฏ)โโ โซ๏ธูพุฑุฏุงุฎุช ูุฌู ุฏุฑุจ ููุฒู ูพุณ ุงุฒ ุชุงุฏ ฺฉุงุฑุดูุงุณ ูุฏ ูุธุฑ ุดูุง โซ๏ธฺฉ ุณุงู ุจูู ุดุฎุต ุซุงูุซุฺฏุงุฑุงูุช ฺฉุงูู ุดุฑฺฉุช ู ูุนุงู โซ๏ธุณูุฏ ุขุฒุงุฏ โซ๏ธูุฒูู ุงูุชูุงู ุณูุฏ ุจุนูุฏู ูุฌููุนู โซ๏ธุณุงุนุช ฺฉุงุฑ | ธ~ูขู|",
    "ฺฉุงุฑฺฉุฑุฏ": "ุตูุฑ ฺฉูููุชุฑ",
    "ููุน ุณูุฎุช": "ุจูุฒู",
    "ฺฏุฑุจฺฉุณ": "ุฏูุฏู ุง",
    "ูุถุนุช ุจุฏูู": "ุจุฏูู ุฑูฺฏ",
    "ุฑูฺฏ ุจุฏูู": "ุณูุฏ",
    "ุฑูฺฏ ุฏุงุฎู": "ุฏุงุฎู ูุดฺฉ",
    "ุญุฌู ููุชูุฑ": "1.6 ูุชุฑ",
    "ูพุดุฑุงูู": "4 ุณููุฏุฑ TU5",
    "ุดุชุงุจ": "11.6 ุซุงูู",
    "ูุตุฑู ุชุฑฺฉุจ": "6.6 ูุชุฑ ุฏุฑ ุตุฏ ฺฉูููุชุฑ"
  },
  {
    "ูุงู": "ูพฺูุ 207",
    "ุณุงู ุณุงุฎุช": "1404",
    "ูุฏู": "ูพุงููุฑุงูุง ุฏูุฏู ุง",
    "ุชุงู": "ุฏูุงู ูพุด",
    "ููุช": "ุชูุงูู",
    "ุขุฏุฑุณ": "ุชูุฑุงู / ูุฑุฏุงูุงุฏ",
    "ุชูุถุญุงุช": " ุชูุถุญุงุช โซ๏ธุดูุงุฑู ุซุจุช (ถฒนถฑฐ) ู ุฏุงุฑุง ุดูุงุณู ูู โโ (ุจุฏูู ฺฉูุณูู ู ฺฉุงุฑูุฒุฏ)โโ โซ๏ธูพุฑุฏุงุฎุช ูุฌู ุฏุฑุจ ููุฒู ูพุณ ุงุฒ ุชุงุฏ ฺฉุงุฑุดูุงุณ ูุฏ ูุธุฑ ุดูุง โซ๏ธฺฉ ุณุงู ุจูู ุดุฎุต ุซุงูุซุฺฏุงุฑุงูุช ฺฉุงูู ุดุฑฺฉุช ู ูุนุงู โซ๏ธุณูุฏ ุขุฒุงุฏ โซ๏ธูุฒูู ุงูุชูุงู ุณูุฏ ุจุนูุฏู ูุฌููุนู โซ๏ธุณุงุนุช ฺฉุงุฑ | ธ~ูขู|",
    "ฺฉุงุฑฺฉุฑุฏ": "ุตูุฑ ฺฉูููุชุฑ",
    "ููุน ุณูุฎุช": "ุจูุฒู",
    "ฺฏุฑุจฺฉุณ": "ุฏูุฏู ุง",
    "ูุถุนุช ุจุฏูู": "ุจุฏูู ุฑูฺฏ",
    "ุฑูฺฏ ุจุฏูู": "ูุดฺฉ",
    "ุฑูฺฏ ุฏุงุฎู": "ุฏุงุฎู ูุดฺฉ",
    "ุญุฌู ููุชูุฑ": "1.6 ูุชุฑ",
    "ูพุดุฑุงูู": "4 ุณููุฏุฑ TU5",
    "ุดุชุงุจ": "11.6 ุซุงูู",
    "ูุตุฑู ุชุฑฺฉุจ": "6.6 ูุชุฑ ุฏุฑ ุตุฏ ฺฉูููุชุฑ"
  },
  {
    "ูุงู": "ูพฺูุ 207",
    "ุณุงู ุณุงุฎุช": "1404",
    "ูุฏู": "ูพุงููุฑุงูุง ุฏูุฏู ุง",
    "ุชุงู": "ุฏูุงู ูพุด",
    "ููุช": "ุชูุงูู",
    "ุขุฏุฑุณ": "ุชูุฑุงู / ูุฑุฏุงูุงุฏ",
    "ุชูุถุญุงุช": " ุชูุถุญุงุช โซ๏ธุดูุงุฑู ุซุจุช (ถฒนถฑฐ) ู ุฏุงุฑุง ุดูุงุณู ูู โโ (ุจุฏูู ฺฉูุณูู ู ฺฉุงุฑูุฒุฏ)โโ โซ๏ธูพุฑุฏุงุฎุช ูุฌู ุฏุฑุจ ููุฒู ูพุณ ุงุฒ ุชุงุฏ ฺฉุงุฑุดูุงุณ ูุฏ ูุธุฑ ุดูุง โซ๏ธฺฉ ุณุงู ุจูู ุดุฎุต ุซุงูุซุฺฏุงุฑุงูุช ฺฉุงูู ุดุฑฺฉุช ู ูุนุงู โซ๏ธุณูุฏ ุขุฒุงุฏ โซ๏ธูุฒูู ุงูุชูุงู ุณูุฏ ุจุนูุฏู ูุฌููุนู โซ๏ธุณุงุนุช ฺฉุงุฑ | ธ~ูขู|",
    "ฺฉุงุฑฺฉุฑุฏ": "ุตูุฑ ฺฉูููุชุฑ",
    "ููุน ุณูุฎุช": "ุจูุฒู",
    "ฺฏุฑุจฺฉุณ": "ุฏูุฏู ุง",
    "ูุถุนุช ุจุฏูู": "ุจุฏูู ุฑูฺฏ",
    "ุฑูฺฏ ุจุฏูู": "ุชุชุงููู",
    "ุฑูฺฏ ุฏุงุฎู": "ุฏุงุฎู ูุดฺฉ",
    "ุญุฌู ููุชูุฑ": "1.6 ูุชุฑ",
    "ูพุดุฑุงูู": "4 ุณููุฏุฑ TU5",
    "ุดุชุงุจ": "11.6 ุซุงูู",
    "ูุตุฑู ุชุฑฺฉุจ": "6.6 ูุชุฑ ุฏุฑ ุตุฏ ฺฉูููุชุฑ"
  },
  {
    "ูุงู": "ูพฺูุ 207",
    "ุณุงู ุณุงุฎุช": "1404",
    "ูุฏู": "ูพุงููุฑุงูุง ุงุชููุงุชฺฉ TU5P",
    "ุชุงู": "ุฏูุงู ูพุด",
    "ููุช": "ุชูุงูู",
    "ุขุฏุฑุณ": "ุชูุฑุงู / ูุฑุฏุงูุงุฏ",
    "ุชูุถุญุงุช": " ุชูุถุญุงุช โซุดูุงุฑู ุซุจุช (ถฒนถฑฐ) ู ุฏุงุฑุง ุดูุงุณู ูู โโ (ุจุฏูู ฺฉูุณูู ู ฺฉุงุฑูุฒุฏ)โโ โซูพุฑุฏุงุฎุช ูุฌู ุฏุฑุจ ููุฒู ูพุณ ุงุฒ ุชุงุฏ ฺฉุงุฑุดูุงุณ ูุฏ ูุธุฑ ุดูุง โซฺฉ ุณุงู ุจูู ุดุฎุต ุซุงูุซุฺฏุงุฑุงูุช ฺฉุงูู ุดุฑฺฉุช ู ูุนุงู โซุณูุฏ ุขุฒุงุฏ โซูุฒูู ุงูุชูุงู ุณูุฏ ุจุนูุฏู ูุฌููุนู โซุณุงุนุช ฺฉุงุฑ | ธ~ูขู|",
    "ฺฉุงุฑฺฉุฑุฏ": "ุตูุฑ ฺฉูููุชุฑ",
    "ููุน ุณูุฎุช": "ุจูุฒู",
    "ฺฏุฑุจฺฉุณ": "ุงุชููุงุชฺฉ",
    "ูุถุนุช ุจุฏูู": "ุจุฏูู ุฑูฺฏ",
    "ุฑูฺฏ ุจุฏูู": "ุชุชุงููู",
    "ุฑูฺฏ ุฏุงุฎู": "ุฏุงุฎู ูุดฺฉ"
  },
  {
    "ูุงู": "ูพฺูุ 207",
    "ุณุงู ุณุงุฎุช": "1404",
    "ูุฏู": "ูพุงููุฑุงูุง ุงุชููุงุชฺฉ TU5P",
    "ุชุงู": "ุฏูุงู ูพุด",
    "ููุช": "ุชูุงูู",
    "ุขุฏุฑุณ": "ุชูุฑุงู / ูุฑุฏุงูุงุฏ",
    "ุชูุถุญุงุช": " ุชูุถุญุงุช โซุดูุงุฑู ุซุจุช (ถฒนถฑฐ) ู ุฏุงุฑุง ุดูุงุณู ูู โโ (ุจุฏูู ฺฉูุณูู ู ฺฉุงุฑูุฒุฏ)โโ โซูพุฑุฏุงุฎุช ูุฌู ุฏุฑุจ ููุฒู ูพุณ ุงุฒ ุชุงุฏ ฺฉุงุฑุดูุงุณ ูุฏ ูุธุฑ ุดูุง โซฺฉ ุณุงู ุจูู ุดุฎุต ุซุงูุซุฺฏุงุฑุงูุช ฺฉุงูู ุดุฑฺฉุช ู ูุนุงู โซุณูุฏ ุขุฒุงุฏ โซูุฒูู ุงูุชูุงู ุณูุฏ ุจุนูุฏู ูุฌููุนู โซุณุงุนุช ฺฉุงุฑ | ธ~ูขู|",
    "ฺฉุงุฑฺฉุฑุฏ": "ุตูุฑ ฺฉูููุชุฑ",
    "ููุน ุณูุฎุช": "ุจูุฒู",
    "ฺฏุฑุจฺฉุณ": "ุงุชููุงุชฺฉ",
    "ูุถุนุช ุจุฏูู": "ุจุฏูู ุฑูฺฏ",
    "ุฑูฺฏ ุจุฏูู": "ุณูุฏ",
    "ุฑูฺฏ ุฏุงุฎู": "ุฏุงุฎู ูุดฺฉ"
  },
  {
    "ูุงู": "ุฏูุงุ ูพูุงุณ EF7",
    "ุณุงู ุณุงุฎุช": "1404",
    "ูุฏู": "ุงุชููุงุชฺฉ ุชูุฑุจู ุขูพุดูุงู",
    "ุชุงู": "ุฏูุงู ูพุด",
    "ููุช": "ุชูุงูู",
    "ุขุฏุฑุณ": "ุชูุฑุงู / ูุฑุฏุงูุงุฏ",
    "ุชูุถุญุงุช": " ุชูุถุญุงุช โซุดูุงุฑู ุซุจุช (ถฒนถฑฐ) ู ุฏุงุฑุง ุดูุงุณู ูู โโ (ุจุฏูู ฺฉูุณูู ู ฺฉุงุฑูุฒุฏ)โโ โซูพุฑุฏุงุฎุช ูุฌู ุฏุฑุจ ููุฒู ูพุณ ุงุฒ ุชุงุฏ ฺฉุงุฑุดูุงุณ ูุฏ ูุธุฑ ุดูุง โซฺฉ ุณุงู ุจูู ุดุฎุต ุซุงูุซุฺฏุงุฑุงูุช ฺฉุงูู ุดุฑฺฉุช ู ูุนุงู โซุณูุฏ ุขุฒุงุฏ โซูุฒูู ุงูุชูุงู ุณูุฏ ุจุนูุฏู ูุฌููุนู โซุณุงุนุช ฺฉุงุฑ | ธ~ูขู|",
    "ฺฉุงุฑฺฉุฑุฏ": "ุตูุฑ ฺฉูููุชุฑ",
    "ููุน ุณูุฎุช": "ุจูุฒู",
    "ฺฏุฑุจฺฉุณ": "ุงุชููุงุชฺฉ",
    "ูุถุนุช ุจุฏูู": "ุจุฏูู ุฑูฺฏ",
    "ุฑูฺฏ ุจุฏูู": "ุชุชุงููู",
    "ุฑูฺฏ ุฏุงุฎู": "ุฏุงุฎู ูุดฺฉ",
    "ุญุฌู ููุชูุฑ": "1.7 ูุชุฑ",
    "ูพุดุฑุงูู": "4 ุณููุฏุฑ ุชูุฑุจูุดุงุฑฺ EF7",
    "ุดุชุงุจ": "10.5 ุซุงูู",
    "ูุตุฑู ุชุฑฺฉุจ": "8.1 ูุชุฑ ุฏุฑ ุตุฏ ฺฉูููุชุฑ"
  },
  {
    "ูุงู": "ุชุงุฑุงุ ุงุชููุงุชฺฉ V4",
    "ุณุงู ุณุงุฎุช": "1404",
    "ูุฏู": "LX",
    "ุชุงู": "ุฏูุงู ูพุด",
    "ููุช": "ุชูุงูู",
    "ุขุฏุฑุณ": "ุชูุฑุงู / ูุฑุฏุงูุงุฏ",
    "ุชูุถุญุงุช": " ุชูุถุญุงุช โซ๏ธุดูุงุฑู ุซุจุช (ถฒนถฑฐ) ู ุฏุงุฑุง ุดูุงุณู ูู โโ (ุจุฏูู ฺฉูุณูู ู ฺฉุงุฑูุฒุฏ)โโ โซ๏ธูพุฑุฏุงุฎุช ูุฌู ุฏุฑุจ ููุฒู ูพุณ ุงุฒ ุชุงุฏ ฺฉุงุฑุดูุงุณ ูุฏ ูุธุฑ ุดูุง โซ๏ธฺฉ ุณุงู ุจูู ุดุฎุต ุซุงูุซุฺฏุงุฑุงูุช ฺฉุงูู ุดุฑฺฉุช ู ูุนุงู โซ๏ธุณูุฏ ุขุฒุงุฏ โซ๏ธูุฒูู ุงูุชูุงู ุณูุฏ ุจุนูุฏู ูุฌููุนู โซ๏ธุณุงุนุช ฺฉุงุฑ | ธ~ูขู|",
    "ฺฉุงุฑฺฉุฑุฏ": "ุตูุฑ ฺฉูููุชุฑ",
    "ููุน ุณูุฎุช": "ุจูุฒู",
    "ฺฏุฑุจฺฉุณ": "ุงุชููุงุชฺฉ",
    "ูุถุนุช ุจุฏูู": "ุจุฏูู ุฑูฺฏ",
    "ุฑูฺฏ ุจุฏูู": "ุณูุฏ",
    "ุฑูฺฏ ุฏุงุฎู": "ุฏุงุฎู ูุดฺฉ",
    "ุญุฌู ููุชูุฑ": "1.6 ูุชุฑ",
    "ูพุดุฑุงูู": "4 ุณููุฏุฑ TU5 ูพูุงุณ",
    "ุดุชุงุจ": "13 ุซุงูู",
    "ูุตุฑู ุชุฑฺฉุจ": "7.3 ูุชุฑ ุฏุฑ ุตุฏ ฺฉูููุชุฑ"
  },
  {
    "ูุงู": "ุชุงุฑุงุ ุฏูุฏู ุง V1 ูพูุงุณ",
    "ุณุงู ุณุงุฎุช": "1404",
    "ูุฏู": "6 ุณุฑุนุชู",
    "ุชุงู": "ุฏูุงู ูพุด",
    "ููุช": "ุชูุงูู",
    "ุขุฏุฑุณ": "ุชูุฑุงู / ูุฑุฏุงูุงุฏ",
    "ุชูุถุญุงุช": " ุชูุถุญุงุช โซ๏ธุดูุงุฑู ุซุจุช (ถฒนถฑฐ) ู ุฏุงุฑุง ุดูุงุณู ูู โโ (ุจุฏูู ฺฉูุณูู ู ฺฉุงุฑูุฒุฏ)โโ โซ๏ธูพุฑุฏุงุฎุช ูุฌู ุฏุฑุจ ููุฒู ูพุณ ุงุฒ ุชุงุฏ ฺฉุงุฑุดูุงุณ ูุฏ ูุธุฑ ุดูุง โซ๏ธฺฉ ุณุงู ุจูู ุดุฎุต ุซุงูุซุฺฏุงุฑุงูุช ฺฉุงูู ุดุฑฺฉุช ู ูุนุงู โซ๏ธุณูุฏ ุขุฒุงุฏ โซ๏ธูุฒูู ุงูุชูุงู ุณูุฏ ุจุนูุฏู ูุฌููุนู โซ๏ธุณุงุนุช ฺฉุงุฑ | ธ~ูขู|",
    "ฺฉุงุฑฺฉุฑุฏ": "ุตูุฑ ฺฉูููุชุฑ",
    "ููุน ุณูุฎุช": "ุจูุฒู",
    "ฺฏุฑุจฺฉุณ": "ุฏูุฏู ุง",
    "ูุถุนุช ุจุฏูู": "ุจุฏูู ุฑูฺฏ",
    "ุฑูฺฏ ุจุฏูู": "ูุดฺฉ",
    "ุฑูฺฏ ุฏุงุฎู": "ุฏุงุฎู ูุดฺฉ",
    "ุญุฌู ููุชูุฑ": "1.6 ูุชุฑ",
    "ูพุดุฑุงูู": "4 ุณููุฏุฑ TU5 ูพูุงุณ",
    "ุดุชุงุจ": "12.5 ุซุงูู",
    "ูุตุฑู ุชุฑฺฉุจ": "7.1 ูุชุฑ ุฏุฑ ุตุฏ ฺฉูููุชุฑ"
  },
  {
    "ูุงู": "ุชุงุฑุงุ ุงุชููุงุชฺฉ V4",
    "ุณุงู ุณุงุฎุช": "1404",
    "ูุฏู": "LX",
    "ุชุงู": "ุฏูุงู ูพุด",
    "ููุช": "ุชูุงูู",
    "ุขุฏุฑุณ": "ุชูุฑุงู / ูุฑุฏุงูุงุฏ",
    "ุชูุถุญุงุช": " ุชูุถุญุงุช โซ๏ธุดูุงุฑู ุซุจุช (ถฒนถฑฐ) ู ุฏุงุฑุง ุดูุงุณู ูู โโ (ุจุฏูู ฺฉูุณูู ู ฺฉุงุฑูุฒุฏ)โโ โซ๏ธูพุฑุฏุงุฎุช ูุฌู ุฏุฑุจ ููุฒู ูพุณ ุงุฒ ุชุงุฏ ฺฉุงุฑุดูุงุณ ูุฏ ูุธุฑ ุดูุง โซ๏ธฺฉ ุณุงู ุจูู ุดุฎุต ุซุงูุซุฺฏุงุฑุงูุช ฺฉุงูู ุดุฑฺฉุช ู ูุนุงู โซ๏ธุณูุฏ ุขุฒุงุฏ โซ๏ธูุฒูู ุงูุชูุงู ุณูุฏ ุจุนูุฏู ูุฌููุนู โซ๏ธุณุงุนุช ฺฉุงุฑ | ธ~ูขู|",
    "ฺฉุงุฑฺฉุฑุฏ": "ุตูุฑ ฺฉูููุชุฑ",
    "ููุน ุณูุฎุช": "ุจูุฒู",
    "ฺฏุฑุจฺฉุณ": "ุงุชููุงุชฺฉ",
    "ูุถุนุช ุจุฏูู": "ุจุฏูู ุฑูฺฏ",
    "ุฑูฺฏ ุจุฏูู": "ุชุชุงููู",
    "ุฑูฺฏ ุฏุงุฎู": "ุฏุงุฎู ูุดฺฉ",
    "ุญุฌู ููุชูุฑ": "1.6 ูุชุฑ",
    "ูพุดุฑุงูู": "4 ุณููุฏุฑ TU5 ูพูุงุณ",
    "ุดุชุงุจ": "13 ุซุงูู",
    "ูุตุฑู ุชุฑฺฉุจ": "7.3 ูุชุฑ ุฏุฑ ุตุฏ ฺฉูููุชุฑ"
  },
  {
    "ูุงู": "ุฏูุงุ ูพูุงุณ EF7",
    "ุณุงู ุณุงุฎุช": "1404",
    "ูุฏู": "ุงุชููุงุชฺฉ ุชูุฑุจู ุขูพุดูุงู",
    "ุชุงู": "ุฏูุงู ูพุด",
    "ููุช": "ุชูุงูู",
    "ุขุฏุฑุณ": "ุชูุฑุงู / ูุฑุฏุงูุงุฏ",
    "ุชูุถุญุงุช": " ุชูุถุญุงุช โซ๏ธุดูุงุฑู ุซุจุช (ถฒนถฑฐ) ู ุฏุงุฑุง ุดูุงุณู ูู โโ (ุจุฏูู ฺฉูุณูู ู ฺฉุงุฑูุฒุฏ)โโ โซ๏ธูพุฑุฏุงุฎุช ูุฌู ุฏุฑุจ ููุฒู ูพุณ ุงุฒ ุชุงุฏ ฺฉุงุฑุดูุงุณ ูุฏ ูุธุฑ ุดูุง โซ๏ธฺฉ ุณุงู ุจูู ุดุฎุต ุซุงูุซุฺฏุงุฑุงูุช ฺฉุงูู ุดุฑฺฉุช ู ูุนุงู โซ๏ธุณูุฏ ุขุฒุงุฏ โซ๏ธูุฒูู ุงูุชูุงู ุณูุฏ ุจุนูุฏู ูุฌููุนู โซ๏ธุณุงุนุช ฺฉุงุฑ | ธ~ูขู|",
    "ฺฉุงุฑฺฉุฑุฏ": "ุตูุฑ ฺฉูููุชุฑ",
    "ููุน ุณูุฎุช": "ุจูุฒู",
    "ฺฏุฑุจฺฉุณ": "ุงุชููุงุชฺฉ",
    "ูุถุนุช ุจุฏูู": "ุจุฏูู ุฑูฺฏ",
    "ุฑูฺฏ ุจุฏูู": "ุณูุฏ",
    "ุฑูฺฏ ุฏุงุฎู": "ุฏุงุฎู ูุดฺฉ",
    "ุญุฌู ููุชูุฑ": "1.7 ูุชุฑ",
    "ูพุดุฑุงูู": "4 ุณููุฏุฑ ุชูุฑุจูุดุงุฑฺ EF7",
    "ุดุชุงุจ": "10.5 ุซุงูู",
    "ูุตุฑู ุชุฑฺฉุจ": "8.1 ูุชุฑ ุฏุฑ ุตุฏ ฺฉูููุชุฑ"
  }
]